Workbook

Sheet Gantt
A1: Planning — Diagramme de Gantt (charge en heures)
A2: Planning de 09/2026 à 02/2028. Cellules jaunes pâles = saisie ; une cellule mois > 0 colore la barre. Ajouter une tâche = remplir une ligne vide ; ajouter un projet, une personne ou une source = onglets dédiés.
A3: Lot | B3: Projet | C3: Tâche | D3: Responsable | E3: Statut | F3: Financement | G3: Charge | H3: Début | I3: Fin | J3: 46266 | K3: 46296 | L3: 46327 | M3: 46357 | N3: 46388 | O3: 46419 | P3: 46447 | Q3: 46478 | R3: 46508 | S3: 46539 | T3: 46569 | U3: 46600 | V3: 46631 | W3: 46661 | X3: 46692 | Y3: 46722 | Z3: 46753 | AA3: 46784 | AC3: Avancement | AD3: Tâches | AE3: Heures
A4: Lot 1 | B4: Projet A | C4: Conception d'actifs 3D | D4: Personne A | E4: En cours | F4: {=IF($C4="","",IFERROR(_xlfn.TEXTJOIN(" + ",TRUE(),IF(Répartition!$A$4:$A$103=$C4,Répartition!$B$4:$B$103&" ("&Répartition!$C$4:$C$103&"h)","")),""))} -> Interne (120h) | G4: =IF(COUNT(J4:AA4)=0,"",SUM(J4:AA4)) -> 120 | H4: =IFERROR(INDEX($J$3:$AA$3,MATCH(TRUE(),INDEX(J4:AA4>0,0),0)),"") -> 46266 | I4: =IF(SUMPRODUCT(MAX((J4:AA4>0)*COLUMN(J4:AA4)))=0,"",INDEX($J$3:$AA$3,SUMPRODUCT(MAX((J4:AA4>0)*COLUMN(J4:AA4)))-COLUMN($J$3)+1)) -> 46296 | J4: 80 | K4: 40 | AC4: Non commencé | AD4: =COUNTIF($E$4:$E$33,AC4) -> 4 | AE4: =SUMIF($E$4:$E$33,AC4,$G$4:$G$33) -> 1500
A5: Lot 5 | B5: Projet A | C5: Modélisation système | D5: Personne A | E5: Non commencé | F5: {=IF($C5="","",IFERROR(_xlfn.TEXTJOIN(" + ",TRUE(),IF(Répartition!$A$4:$A$103=$C5,Répartition!$B$4:$B$103&" ("&Répartition!$C$4:$C$103&"h)","")),""))} -> Interne (200h) | G5: =IF(COUNT(J5:AA5)=0,"",SUM(J5:AA5)) -> 200 | H5: =IFERROR(INDEX($J$3:$AA$3,MATCH(TRUE(),INDEX(J5:AA5>0,0),0)),"") -> 46296 | I5: =IF(SUMPRODUCT(MAX((J5:AA5>0)*COLUMN(J5:AA5)))=0,"",INDEX($J$3:$AA$3,SUMPRODUCT(MAX((J5:AA5>0)*COLUMN(J5:AA5)))-COLUMN($J$3)+1)) -> 46296 | K5: 200 | AC5: En cours | AD5: =COUNTIF($E$4:$E$33,AC5) -> 1 | AE5: =SUMIF($E$4:$E$33,AC5,$G$4:$G$33) -> 120
A6: Lot 2 | B6: Projet B | C6: Intégration technique | D6: Personne B | E6: Non commencé | F6: {=IF($C6="","",IFERROR(_xlfn.TEXTJOIN(" + ",TRUE(),IF(Répartition!$A$4:$A$103=$C6,Répartition!$B$4:$B$103&" ("&Répartition!$C$4:$C$103&"h)","")),""))} -> Client A (300h) + Subvention (180h) | G6: =IF(COUNT(J6:AA6)=0,"",SUM(J6:AA6)) -> 480 | H6: =IFERROR(INDEX($J$3:$AA$3,MATCH(TRUE(),INDEX(J6:AA6>0,0),0)),"") -> 46296 | I6: =IF(SUMPRODUCT(MAX((J6:AA6>0)*COLUMN(J6:AA6)))=0,"",INDEX($J$3:$AA$3,SUMPRODUCT(MAX((J6:AA6>0)*COLUMN(J6:AA6)))-COLUMN($J$3)+1)) -> 46357 | K6: 80 | L6: 320 | M6: 80 | AC6: Réalisé | AD6: =COUNTIF($E$4:$E$33,AC6) -> 0 | AE6: =SUMIF($E$4:$E$33,AC6,$G$4:$G$33) -> 0
A7: Lot 3 | B7: Projet B | C7: Configuration scénarios | D7: Personne B | E7: Non commencé | F7: {=IF($C7="","",IFERROR(_xlfn.TEXTJOIN(" + ",TRUE(),IF(Répartition!$A$4:$A$103=$C7,Répartition!$B$4:$B$103&" ("&Répartition!$C$4:$C$103&"h)","")),""))} -> Client A (500h) | G7: =IF(COUNT(J7:AA7)=0,"",SUM(J7:AA7)) -> 500 | H7: =IFERROR(INDEX($J$3:$AA$3,MATCH(TRUE(),INDEX(J7:AA7>0,0),0)),"") -> 46357 | I7: =IF(SUMPRODUCT(MAX((J7:AA7>0)*COLUMN(J7:AA7)))=0,"",INDEX($J$3:$AA$3,SUMPRODUCT(MAX((J7:AA7>0)*COLUMN(J7:AA7)))-COLUMN($J$3)+1)) -> 46388 | L7: 0 | M7: 240 | N7: 260 | AC7: % réalisé (h) | AE7: =IFERROR(AE6/SUM(AE4:AE6),0) -> 0
A8: Lot 4 | B8: Projet A | C8: Préparation livraison | D8: Personne A | E8: Non commencé | F8: {=IF($C8="","",IFERROR(_xlfn.TEXTJOIN(" + ",TRUE(),IF(Répartition!$A$4:$A$103=$C8,Répartition!$B$4:$B$103&" ("&Répartition!$C$4:$C$103&"h)","")),""))} -> Client A (220h) + Client B (100h) | G8: =IF(COUNT(J8:AA8)=0,"",SUM(J8:AA8)) -> 320 | H8: =IFERROR(INDEX($J$3:$AA$3,MATCH(TRUE(),INDEX(J8:AA8>0,0),0)),"") -> 46388 | I8: =IF(SUMPRODUCT(MAX((J8:AA8>0)*COLUMN(J8:AA8)))=0,"",INDEX($J$3:$AA$3,SUMPRODUCT(MAX((J8:AA8>0)*COLUMN(J8:AA8)))-COLUMN($J$3)+1)) -> 46419 | N8: 60 | O8: 260
F9: {=IF($C9="","",IFERROR(_xlfn.TEXTJOIN(" + ",TRUE(),IF(Répartition!$A$4:$A$103=$C9,Répartition!$B$4:$B$103&" ("&Répartition!$C$4:$C$103&"h)","")),""))} | G9: =IF(COUNT(J9:AA9)=0,"",SUM(J9:AA9)) | H9: =IFERROR(INDEX($J$3:$AA$3,MATCH(TRUE(),INDEX(J9:AA9>0,0),0)),"") | I9: =IF(SUMPRODUCT(MAX((J9:AA9>0)*COLUMN(J9:AA9)))=0,"",INDEX($J$3:$AA$3,SUMPRODUCT(MAX((J9:AA9>0)*COLUMN(J9:AA9)))-COLUMN($J$3)+1))
F10: {=IF($C10="","",IFERROR(_xlfn.TEXTJOIN(" + ",TRUE(),IF(Répartition!$A$4:$A$103=$C10,Répartition!$B$4:$B$103&" ("&Répartition!$C$4:$C$103&"h)","")),""))} | G10: =IF(COUNT(J10:AA10)=0,"",SUM(J10:AA10)) | H10: =IFERROR(INDEX($J$3:$AA$3,MATCH(TRUE(),INDEX(J10:AA10>0,0),0)),"") | I10: =IF(SUMPRODUCT(MAX((J10:AA10>0)*COLUMN(J10:AA10)))=0,"",INDEX($J$3:$AA$3,SUMPRODUCT(MAX((J10:AA10>0)*COLUMN(J10:AA10)))-COLUMN($J$3)+1))
F11: {=IF($C11="","",IFERROR(_xlfn.TEXTJOIN(" + ",TRUE(),IF(Répartition!$A$4:$A$103=$C11,Répartition!$B$4:$B$103&" ("&Répartition!$C$4:$C$103&"h)","")),""))} | G11: =IF(COUNT(J11:AA11)=0,"",SUM(J11:AA11)) | H11: =IFERROR(INDEX($J$3:$AA$3,MATCH(TRUE(),INDEX(J11:AA11>0,0),0)),"") | I11: =IF(SUMPRODUCT(MAX((J11:AA11>0)*COLUMN(J11:AA11)))=0,"",INDEX($J$3:$AA$3,SUMPRODUCT(MAX((J11:AA11>0)*COLUMN(J11:AA11)))-COLUMN($J$3)+1))
F12: {=IF($C12="","",IFERROR(_xlfn.TEXTJOIN(" + ",TRUE(),IF(Répartition!$A$4:$A$103=$C12,Répartition!$B$4:$B$103&" ("&Répartition!$C$4:$C$103&"h)","")),""))} | G12: =IF(COUNT(J12:AA12)=0,"",SUM(J12:AA12)) | H12: =IFERROR(INDEX($J$3:$AA$3,MATCH(TRUE(),INDEX(J12:AA12>0,0),0)),"") | I12: =IF(SUMPRODUCT(MAX((J12:AA12>0)*COLUMN(J12:AA12)))=0,"",INDEX($J$3:$AA$3,SUMPRODUCT(MAX((J12:AA12>0)*COLUMN(J12:AA12)))-COLUMN($J$3)+1))
F13: {=IF($C13="","",IFERROR(_xlfn.TEXTJOIN(" + ",TRUE(),IF(Répartition!$A$4:$A$103=$C13,Répartition!$B$4:$B$103&" ("&Répartition!$C$4:$C$103&"h)","")),""))} | G13: =IF(COUNT(J13:AA13)=0,"",SUM(J13:AA13)) | H13: =IFERROR(INDEX($J$3:$AA$3,MATCH(TRUE(),INDEX(J13:AA13>0,0),0)),"") | I13: =IF(SUMPRODUCT(MAX((J13:AA13>0)*COLUMN(J13:AA13)))=0,"",INDEX($J$3:$AA$3,SUMPRODUCT(MAX((J13:AA13>0)*COLUMN(J13:AA13)))-COLUMN($J$3)+1))
F14: {=IF($C14="","",IFERROR(_xlfn.TEXTJOIN(" + ",TRUE(),IF(Répartition!$A$4:$A$103=$C14,Répartition!$B$4:$B$103&" ("&Répartition!$C$4:$C$103&"h)","")),""))} | G14: =IF(COUNT(J14:AA14)=0,"",SUM(J14:AA14)) | H14: =IFERROR(INDEX($J$3:$AA$3,MATCH(TRUE(),INDEX(J14:AA14>0,0),0)),"") | I14: =IF(SUMPRODUCT(MAX((J14:AA14>0)*COLUMN(J14:AA14)))=0,"",INDEX($J$3:$AA$3,SUMPRODUCT(MAX((J14:AA14>0)*COLUMN(J14:AA14)))-COLUMN($J$3)+1))
F15: {=IF($C15="","",IFERROR(_xlfn.TEXTJOIN(" + ",TRUE(),IF(Répartition!$A$4:$A$103=$C15,Répartition!$B$4:$B$103&" ("&Répartition!$C$4:$C$103&"h)","")),""))} | G15: =IF(COUNT(J15:AA15)=0,"",SUM(J15:AA15)) | H15: =IFERROR(INDEX($J$3:$AA$3,MATCH(TRUE(),INDEX(J15:AA15>0,0),0)),"") | I15: =IF(SUMPRODUCT(MAX((J15:AA15>0)*COLUMN(J15:AA15)))=0,"",INDEX($J$3:$AA$3,SUMPRODUCT(MAX((J15:AA15>0)*COLUMN(J15:AA15)))-COLUMN($J$3)+1))
F16: {=IF($C16="","",IFERROR(_xlfn.TEXTJOIN(" + ",TRUE(),IF(Répartition!$A$4:$A$103=$C16,Répartition!$B$4:$B$103&" ("&Répartition!$C$4:$C$103&"h)","")),""))} | G16: =IF(COUNT(J16:AA16)=0,"",SUM(J16:AA16)) | H16: =IFERROR(INDEX($J$3:$AA$3,MATCH(TRUE(),INDEX(J16:AA16>0,0),0)),"") | I16: =IF(SUMPRODUCT(MAX((J16:AA16>0)*COLUMN(J16:AA16)))=0,"",INDEX($J$3:$AA$3,SUMPRODUCT(MAX((J16:AA16>0)*COLUMN(J16:AA16)))-COLUMN($J$3)+1))
F17: {=IF($C17="","",IFERROR(_xlfn.TEXTJOIN(" + ",TRUE(),IF(Répartition!$A$4:$A$103=$C17,Répartition!$B$4:$B$103&" ("&Répartition!$C$4:$C$103&"h)","")),""))} | G17: =IF(COUNT(J17:AA17)=0,"",SUM(J17:AA17)) | H17: =IFERROR(INDEX($J$3:$AA$3,MATCH(TRUE(),INDEX(J17:AA17>0,0),0)),"") | I17: =IF(SUMPRODUCT(MAX((J17:AA17>0)*COLUMN(J17:AA17)))=0,"",INDEX($J$3:$AA$3,SUMPRODUCT(MAX((J17:AA17>0)*COLUMN(J17:AA17)))-COLUMN($J$3)+1))
F18: {=IF($C18="","",IFERROR(_xlfn.TEXTJOIN(" + ",TRUE(),IF(Répartition!$A$4:$A$103=$C18,Répartition!$B$4:$B$103&" ("&Répartition!$C$4:$C$103&"h)","")),""))} | G18: =IF(COUNT(J18:AA18)=0,"",SUM(J18:AA18)) | H18: =IFERROR(INDEX($J$3:$AA$3,MATCH(TRUE(),INDEX(J18:AA18>0,0),0)),"") | I18: =IF(SUMPRODUCT(MAX((J18:AA18>0)*COLUMN(J18:AA18)))=0,"",INDEX($J$3:$AA$3,SUMPRODUCT(MAX((J18:AA18>0)*COLUMN(J18:AA18)))-COLUMN($J$3)+1))
F19: {=IF($C19="","",IFERROR(_xlfn.TEXTJOIN(" + ",TRUE(),IF(Répartition!$A$4:$A$103=$C19,Répartition!$B$4:$B$103&" ("&Répartition!$C$4:$C$103&"h)","")),""))} | G19: =IF(COUNT(J19:AA19)=0,"",SUM(J19:AA19)) | H19: =IFERROR(INDEX($J$3:$AA$3,MATCH(TRUE(),INDEX(J19:AA19>0,0),0)),"") | I19: =IF(SUMPRODUCT(MAX((J19:AA19>0)*COLUMN(J19:AA19)))=0,"",INDEX($J$3:$AA$3,SUMPRODUCT(MAX((J19:AA19>0)*COLUMN(J19:AA19)))-COLUMN($J$3)+1))
F20: {=IF($C20="","",IFERROR(_xlfn.TEXTJOIN(" + ",TRUE(),IF(Répartition!$A$4:$A$103=$C20,Répartition!$B$4:$B$103&" ("&Répartition!$C$4:$C$103&"h)","")),""))} | G20: =IF(COUNT(J20:AA20)=0,"",SUM(J20:AA20)) | H20: =IFERROR(INDEX($J$3:$AA$3,MATCH(TRUE(),INDEX(J20:AA20>0,0),0)),"") | I20: =IF(SUMPRODUCT(MAX((J20:AA20>0)*COLUMN(J20:AA20)))=0,"",INDEX($J$3:$AA$3,SUMPRODUCT(MAX((J20:AA20>0)*COLUMN(J20:AA20)))-COLUMN($J$3)+1))
... F33: {=IF($C33="","",IFERROR(_xlfn.TEXTJOIN(" + ",TRUE(),IF(Répartition!$A$4:$A$103=$C33,Répartition!$B$4:$B$103&" ("&Répartition!$C$4:$C$103&"h)","")),""))} | G33: =IF(COUNT(J33:AA33)=0,"",SUM(J33:AA33)) | H33: =IFERROR(INDEX($J$3:$AA$3,MATCH(TRUE(),INDEX(J33:AA33>0,0),0)),"") | I33: =IF(SUMPRODUCT(MAX((J33:AA33>0)*COLUMN(J33:AA33)))=0,"",INDEX($J$3:$AA$3,SUMPRODUCT(MAX((J33:AA33>0)*COLUMN(J33:AA33)))-COLUMN($J$3)+1))
A34: TOTAL | G34: =SUM(G4:G33) -> 1620 | J34: =SUM(J4:J33) -> 80 | K34: =SUM(K4:K33) -> 320 | L34: =SUM(L4:L33) -> 320 | M34: =SUM(M4:M33) -> 320 | N34: =SUM(N4:N33) -> 320 | O34: =SUM(O4:O33) -> 260 | P34: =SUM(P4:P33) -> 0 | Q34: =SUM(Q4:Q33) -> 0 | ... AA34: =SUM(AA4:AA33) -> 0
A36: Jalons & livrables
A37: Type | B37: Projet | C37: Intitulé | D37: Responsable | E37: Statut | F37: Financement | G37: Lot | H37: Échéance | I37: Commentaire | J37: 46266 | K37: 46296 | L37: 46327 | M37: 46357 | N37: 46388 | O37: 46419 | P37: 46447 | Q37: 46478 | R37: 46508 | S37: 46539 | T37: 46569 | U37: 46600 | V37: 46631 | W37: 46661 | X37: 46692 | Y37: 46722 | Z37: 46753 | AA37: 46784
A38: Jalon | B38: Projet A | C38: Revue de conception | D38: Personne A | E38: Non commencé | F38: Interne | G38: Lot 1 | H38: 46296 | J38: =IF($H38=J$37,IF($A38="Jalon","◆",IF($A38="Livrable","▲","●")),"") | K38: =IF($H38=K$37,IF($A38="Jalon","◆",IF($A38="Livrable","▲","●")),"") -> ◆ | L38: =IF($H38=L$37,IF($A38="Jalon","◆",IF($A38="Livrable","▲","●")),"") | M38: =IF($H38=M$37,IF($A38="Jalon","◆",IF($A38="Livrable","▲","●")),"") | N38: =IF($H38=N$37,IF($A38="Jalon","◆",IF($A38="Livrable","▲","●")),"") | O38: =IF($H38=O$37,IF($A38="Jalon","◆",IF($A38="Livrable","▲","●")),"") | P38: =IF($H38=P$37,IF($A38="Jalon","◆",IF($A38="Livrable","▲","●")),"") | Q38: =IF($H38=Q$37,IF($A38="Jalon","◆",IF($A38="Livrable","▲","●")),"") | ... AA38: =IF($H38=AA$37,IF($A38="Jalon","◆",IF($A38="Livrable","▲","●")),"")
A39: Livrable | B39: Projet A | C39: Dossier de livraison | D39: Personne B | E39: Non commencé | F39: Client A | G39: Lot 4 | H39: 46419 | J39: =IF($H39=J$37,IF($A39="Jalon","◆",IF($A39="Livrable","▲","●")),"") | K39: =IF($H39=K$37,IF($A39="Jalon","◆",IF($A39="Livrable","▲","●")),"") | L39: =IF($H39=L$37,IF($A39="Jalon","◆",IF($A39="Livrable","▲","●")),"") | M39: =IF($H39=M$37,IF($A39="Jalon","◆",IF($A39="Livrable","▲","●")),"") | N39: =IF($H39=N$37,IF($A39="Jalon","◆",IF($A39="Livrable","▲","●")),"") | O39: =IF($H39=O$37,IF($A39="Jalon","◆",IF($A39="Livrable","▲","●")),"") -> ▲ | P39: =IF($H39=P$37,IF($A39="Jalon","◆",IF($A39="Livrable","▲","●")),"") | Q39: =IF($H39=Q$37,IF($A39="Jalon","◆",IF($A39="Livrable","▲","●")),"") | ... AA39: =IF($H39=AA$37,IF($A39="Jalon","◆",IF($A39="Livrable","▲","●")),"")
J40: =IF($H40=J$37,IF($A40="Jalon","◆",IF($A40="Livrable","▲","●")),"") | K40: =IF($H40=K$37,IF($A40="Jalon","◆",IF($A40="Livrable","▲","●")),"") | L40: =IF($H40=L$37,IF($A40="Jalon","◆",IF($A40="Livrable","▲","●")),"") | M40: =IF($H40=M$37,IF($A40="Jalon","◆",IF($A40="Livrable","▲","●")),"") | N40: =IF($H40=N$37,IF($A40="Jalon","◆",IF($A40="Livrable","▲","●")),"") | O40: =IF($H40=O$37,IF($A40="Jalon","◆",IF($A40="Livrable","▲","●")),"") | P40: =IF($H40=P$37,IF($A40="Jalon","◆",IF($A40="Livrable","▲","●")),"") | Q40: =IF($H40=Q$37,IF($A40="Jalon","◆",IF($A40="Livrable","▲","●")),"") | ... AA40: =IF($H40=AA$37,IF($A40="Jalon","◆",IF($A40="Livrable","▲","●")),"")
J41: =IF($H41=J$37,IF($A41="Jalon","◆",IF($A41="Livrable","▲","●")),"") | K41: =IF($H41=K$37,IF($A41="Jalon","◆",IF($A41="Livrable","▲","●")),"") | L41: =IF($H41=L$37,IF($A41="Jalon","◆",IF($A41="Livrable","▲","●")),"") | M41: =IF($H41=M$37,IF($A41="Jalon","◆",IF($A41="Livrable","▲","●")),"") | N41: =IF($H41=N$37,IF($A41="Jalon","◆",IF($A41="Livrable","▲","●")),"") | O41: =IF($H41=O$37,IF($A41="Jalon","◆",IF($A41="Livrable","▲","●")),"") | P41: =IF($H41=P$37,IF($A41="Jalon","◆",IF($A41="Livrable","▲","●")),"") | Q41: =IF($H41=Q$37,IF($A41="Jalon","◆",IF($A41="Livrable","▲","●")),"") | ... AA41: =IF($H41=AA$37,IF($A41="Jalon","◆",IF($A41="Livrable","▲","●")),"")
J42: =IF($H42=J$37,IF($A42="Jalon","◆",IF($A42="Livrable","▲","●")),"") | K42: =IF($H42=K$37,IF($A42="Jalon","◆",IF($A42="Livrable","▲","●")),"") | L42: =IF($H42=L$37,IF($A42="Jalon","◆",IF($A42="Livrable","▲","●")),"") | M42: =IF($H42=M$37,IF($A42="Jalon","◆",IF($A42="Livrable","▲","●")),"") | N42: =IF($H42=N$37,IF($A42="Jalon","◆",IF($A42="Livrable","▲","●")),"") | O42: =IF($H42=O$37,IF($A42="Jalon","◆",IF($A42="Livrable","▲","●")),"") | P42: =IF($H42=P$37,IF($A42="Jalon","◆",IF($A42="Livrable","▲","●")),"") | Q42: =IF($H42=Q$37,IF($A42="Jalon","◆",IF($A42="Livrable","▲","●")),"") | ... AA42: =IF($H42=AA$37,IF($A42="Jalon","◆",IF($A42="Livrable","▲","●")),"")
J43: =IF($H43=J$37,IF($A43="Jalon","◆",IF($A43="Livrable","▲","●")),"") | K43: =IF($H43=K$37,IF($A43="Jalon","◆",IF($A43="Livrable","▲","●")),"") | L43: =IF($H43=L$37,IF($A43="Jalon","◆",IF($A43="Livrable","▲","●")),"") | M43: =IF($H43=M$37,IF($A43="Jalon","◆",IF($A43="Livrable","▲","●")),"") | N43: =IF($H43=N$37,IF($A43="Jalon","◆",IF($A43="Livrable","▲","●")),"") | O43: =IF($H43=O$37,IF($A43="Jalon","◆",IF($A43="Livrable","▲","●")),"") | P43: =IF($H43=P$37,IF($A43="Jalon","◆",IF($A43="Livrable","▲","●")),"") | Q43: =IF($H43=Q$37,IF($A43="Jalon","◆",IF($A43="Livrable","▲","●")),"") | ... AA43: =IF($H43=AA$37,IF($A43="Jalon","◆",IF($A43="Livrable","▲","●")),"")
J44: =IF($H44=J$37,IF($A44="Jalon","◆",IF($A44="Livrable","▲","●")),"") | K44: =IF($H44=K$37,IF($A44="Jalon","◆",IF($A44="Livrable","▲","●")),"") | L44: =IF($H44=L$37,IF($A44="Jalon","◆",IF($A44="Livrable","▲","●")),"") | M44: =IF($H44=M$37,IF($A44="Jalon","◆",IF($A44="Livrable","▲","●")),"") | N44: =IF($H44=N$37,IF($A44="Jalon","◆",IF($A44="Livrable","▲","●")),"") | O44: =IF($H44=O$37,IF($A44="Jalon","◆",IF($A44="Livrable","▲","●")),"") | P44: =IF($H44=P$37,IF($A44="Jalon","◆",IF($A44="Livrable","▲","●")),"") | Q44: =IF($H44=Q$37,IF($A44="Jalon","◆",IF($A44="Livrable","▲","●")),"") | ... AA44: =IF($H44=AA$37,IF($A44="Jalon","◆",IF($A44="Livrable","▲","●")),"")
J45: =IF($H45=J$37,IF($A45="Jalon","◆",IF($A45="Livrable","▲","●")),"") | K45: =IF($H45=K$37,IF($A45="Jalon","◆",IF($A45="Livrable","▲","●")),"") | L45: =IF($H45=L$37,IF($A45="Jalon","◆",IF($A45="Livrable","▲","●")),"") | M45: =IF($H45=M$37,IF($A45="Jalon","◆",IF($A45="Livrable","▲","●")),"") | N45: =IF($H45=N$37,IF($A45="Jalon","◆",IF($A45="Livrable","▲","●")),"") | O45: =IF($H45=O$37,IF($A45="Jalon","◆",IF($A45="Livrable","▲","●")),"") | P45: =IF($H45=P$37,IF($A45="Jalon","◆",IF($A45="Livrable","▲","●")),"") | Q45: =IF($H45=Q$37,IF($A45="Jalon","◆",IF($A45="Livrable","▲","●")),"") | ... AA45: =IF($H45=AA$37,IF($A45="Jalon","◆",IF($A45="Livrable","▲","●")),"")
J46: =IF($H46=J$37,IF($A46="Jalon","◆",IF($A46="Livrable","▲","●")),"") | K46: =IF($H46=K$37,IF($A46="Jalon","◆",IF($A46="Livrable","▲","●")),"") | L46: =IF($H46=L$37,IF($A46="Jalon","◆",IF($A46="Livrable","▲","●")),"") | M46: =IF($H46=M$37,IF($A46="Jalon","◆",IF($A46="Livrable","▲","●")),"") | N46: =IF($H46=N$37,IF($A46="Jalon","◆",IF($A46="Livrable","▲","●")),"") | O46: =IF($H46=O$37,IF($A46="Jalon","◆",IF($A46="Livrable","▲","●")),"") | P46: =IF($H46=P$37,IF($A46="Jalon","◆",IF($A46="Livrable","▲","●")),"") | Q46: =IF($H46=Q$37,IF($A46="Jalon","◆",IF($A46="Livrable","▲","●")),"") | ... AA46: =IF($H46=AA$37,IF($A46="Jalon","◆",IF($A46="Livrable","▲","●")),"")
J47: =IF($H47=J$37,IF($A47="Jalon","◆",IF($A47="Livrable","▲","●")),"") | K47: =IF($H47=K$37,IF($A47="Jalon","◆",IF($A47="Livrable","▲","●")),"") | L47: =IF($H47=L$37,IF($A47="Jalon","◆",IF($A47="Livrable","▲","●")),"") | M47: =IF($H47=M$37,IF($A47="Jalon","◆",IF($A47="Livrable","▲","●")),"") | N47: =IF($H47=N$37,IF($A47="Jalon","◆",IF($A47="Livrable","▲","●")),"") | O47: =IF($H47=O$37,IF($A47="Jalon","◆",IF($A47="Livrable","▲","●")),"") | P47: =IF($H47=P$37,IF($A47="Jalon","◆",IF($A47="Livrable","▲","●")),"") | Q47: =IF($H47=Q$37,IF($A47="Jalon","◆",IF($A47="Livrable","▲","●")),"") | ... AA47: =IF($H47=AA$37,IF($A47="Jalon","◆",IF($A47="Livrable","▲","●")),"")
J48: =IF($H48=J$37,IF($A48="Jalon","◆",IF($A48="Livrable","▲","●")),"") | K48: =IF($H48=K$37,IF($A48="Jalon","◆",IF($A48="Livrable","▲","●")),"") | L48: =IF($H48=L$37,IF($A48="Jalon","◆",IF($A48="Livrable","▲","●")),"") | M48: =IF($H48=M$37,IF($A48="Jalon","◆",IF($A48="Livrable","▲","●")),"") | N48: =IF($H48=N$37,IF($A48="Jalon","◆",IF($A48="Livrable","▲","●")),"") | O48: =IF($H48=O$37,IF($A48="Jalon","◆",IF($A48="Livrable","▲","●")),"") | P48: =IF($H48=P$37,IF($A48="Jalon","◆",IF($A48="Livrable","▲","●")),"") | Q48: =IF($H48=Q$37,IF($A48="Jalon","◆",IF($A48="Livrable","▲","●")),"") | ... AA48: =IF($H48=AA$37,IF($A48="Jalon","◆",IF($A48="Livrable","▲","●")),"")
J49: =IF($H49=J$37,IF($A49="Jalon","◆",IF($A49="Livrable","▲","●")),"") | K49: =IF($H49=K$37,IF($A49="Jalon","◆",IF($A49="Livrable","▲","●")),"") | L49: =IF($H49=L$37,IF($A49="Jalon","◆",IF($A49="Livrable","▲","●")),"") | M49: =IF($H49=M$37,IF($A49="Jalon","◆",IF($A49="Livrable","▲","●")),"") | N49: =IF($H49=N$37,IF($A49="Jalon","◆",IF($A49="Livrable","▲","●")),"") | O49: =IF($H49=O$37,IF($A49="Jalon","◆",IF($A49="Livrable","▲","●")),"") | P49: =IF($H49=P$37,IF($A49="Jalon","◆",IF($A49="Livrable","▲","●")),"") | Q49: =IF($H49=Q$37,IF($A49="Jalon","◆",IF($A49="Livrable","▲","●")),"") | ... AA49: =IF($H49=AA$37,IF($A49="Jalon","◆",IF($A49="Livrable","▲","●")),"")
J50: =IF($H50=J$37,IF($A50="Jalon","◆",IF($A50="Livrable","▲","●")),"") | K50: =IF($H50=K$37,IF($A50="Jalon","◆",IF($A50="Livrable","▲","●")),"") | L50: =IF($H50=L$37,IF($A50="Jalon","◆",IF($A50="Livrable","▲","●")),"") | M50: =IF($H50=M$37,IF($A50="Jalon","◆",IF($A50="Livrable","▲","●")),"") | N50: =IF($H50=N$37,IF($A50="Jalon","◆",IF($A50="Livrable","▲","●")),"") | O50: =IF($H50=O$37,IF($A50="Jalon","◆",IF($A50="Livrable","▲","●")),"") | P50: =IF($H50=P$37,IF($A50="Jalon","◆",IF($A50="Livrable","▲","●")),"") | Q50: =IF($H50=Q$37,IF($A50="Jalon","◆",IF($A50="Livrable","▲","●")),"") | ... AA50: =IF($H50=AA$37,IF($A50="Jalon","◆",IF($A50="Livrable","▲","●")),"")
J51: =IF($H51=J$37,IF($A51="Jalon","◆",IF($A51="Livrable","▲","●")),"") | K51: =IF($H51=K$37,IF($A51="Jalon","◆",IF($A51="Livrable","▲","●")),"") | L51: =IF($H51=L$37,IF($A51="Jalon","◆",IF($A51="Livrable","▲","●")),"") | M51: =IF($H51=M$37,IF($A51="Jalon","◆",IF($A51="Livrable","▲","●")),"") | N51: =IF($H51=N$37,IF($A51="Jalon","◆",IF($A51="Livrable","▲","●")),"") | O51: =IF($H51=O$37,IF($A51="Jalon","◆",IF($A51="Livrable","▲","●")),"") | P51: =IF($H51=P$37,IF($A51="Jalon","◆",IF($A51="Livrable","▲","●")),"") | Q51: =IF($H51=Q$37,IF($A51="Jalon","◆",IF($A51="Livrable","▲","●")),"") | ... AA51: =IF($H51=AA$37,IF($A51="Jalon","◆",IF($A51="Livrable","▲","●")),"")
... J57: =IF($H57=J$37,IF($A57="Jalon","◆",IF($A57="Livrable","▲","●")),"") | K57: =IF($H57=K$37,IF($A57="Jalon","◆",IF($A57="Livrable","▲","●")),"") | L57: =IF($H57=L$37,IF($A57="Jalon","◆",IF($A57="Livrable","▲","●")),"") | M57: =IF($H57=M$37,IF($A57="Jalon","◆",IF($A57="Livrable","▲","●")),"") | N57: =IF($H57=N$37,IF($A57="Jalon","◆",IF($A57="Livrable","▲","●")),"") | O57: =IF($H57=O$37,IF($A57="Jalon","◆",IF($A57="Livrable","▲","●")),"") | P57: =IF($H57=P$37,IF($A57="Jalon","◆",IF($A57="Livrable","▲","●")),"") | Q57: =IF($H57=Q$37,IF($A57="Jalon","◆",IF($A57="Livrable","▲","●")),"") | ... AA57: =IF($H57=AA$37,IF($A57="Jalon","◆",IF($A57="Livrable","▲","●")),"")
A59: Légende : ◆ jalon ▲ livrable ● revue — vert = réalisé. Case de tâche encadrée = jalon/livrable du même lot ce mois-là. Statuts : gris non commencé, orange en cours, vert réalisé.

Sheet Équipe
A1: Équipe — charge par personne (h)
A3: Personne | B3: Rôle | C3: Charge totale | D3: 46266 | E3: 46296 | F3: 46327 | G3: 46357 | H3: 46388 | I3: 46419 | J3: 46447 | K3: 46478 | L3: 46508 | M3: 46539 | N3: 46569 | O3: 46600 | P3: 46631 | Q3: 46661 | R3: 46692 | S3: 46722 | T3: 46753 | U3: 46784
A4: Personne A | B4: Architecte / modélisation | C4: =IF(A4="","",SUMIF(Gantt!$D$4:$D$33,A4,Gantt!$G$4:$G$33)) -> 640 | D4: =IF($A4="","",SUMIF(Gantt!$D$4:$D$33,$A4,Gantt!J$4:J$33)) -> 80 | E4: =IF($A4="","",SUMIF(Gantt!$D$4:$D$33,$A4,Gantt!K$4:K$33)) -> 240 | F4: =IF($A4="","",SUMIF(Gantt!$D$4:$D$33,$A4,Gantt!L$4:L$33)) -> 0 | G4: =IF($A4="","",SUMIF(Gantt!$D$4:$D$33,$A4,Gantt!M$4:M$33)) -> 0 | H4: =IF($A4="","",SUMIF(Gantt!$D$4:$D$33,$A4,Gantt!N$4:N$33)) -> 60 | I4: =IF($A4="","",SUMIF(Gantt!$D$4:$D$33,$A4,Gantt!O$4:O$33)) -> 260 | J4: =IF($A4="","",SUMIF(Gantt!$D$4:$D$33,$A4,Gantt!P$4:P$33)) -> 0 | K4: =IF($A4="","",SUMIF(Gantt!$D$4:$D$33,$A4,Gantt!Q$4:Q$33)) -> 0 | ... U4: =IF($A4="","",SUMIF(Gantt!$D$4:$D$33,$A4,Gantt!AA$4:AA$33)) -> 0
A5: Personne B | B5: Développeur intégration | C5: =IF(A5="","",SUMIF(Gantt!$D$4:$D$33,A5,Gantt!$G$4:$G$33)) -> 980 | D5: =IF($A5="","",SUMIF(Gantt!$D$4:$D$33,$A5,Gantt!J$4:J$33)) -> 0 | E5: =IF($A5="","",SUMIF(Gantt!$D$4:$D$33,$A5,Gantt!K$4:K$33)) -> 80 | F5: =IF($A5="","",SUMIF(Gantt!$D$4:$D$33,$A5,Gantt!L$4:L$33)) -> 320 | G5: =IF($A5="","",SUMIF(Gantt!$D$4:$D$33,$A5,Gantt!M$4:M$33)) -> 320 | H5: =IF($A5="","",SUMIF(Gantt!$D$4:$D$33,$A5,Gantt!N$4:N$33)) -> 260 | I5: =IF($A5="","",SUMIF(Gantt!$D$4:$D$33,$A5,Gantt!O$4:O$33)) -> 0 | J5: =IF($A5="","",SUMIF(Gantt!$D$4:$D$33,$A5,Gantt!P$4:P$33)) -> 0 | K5: =IF($A5="","",SUMIF(Gantt!$D$4:$D$33,$A5,Gantt!Q$4:Q$33)) -> 0 | ... U5: =IF($A5="","",SUMIF(Gantt!$D$4:$D$33,$A5,Gantt!AA$4:AA$33)) -> 0
C6: =IF(A6="","",SUMIF(Gantt!$D$4:$D$33,A6,Gantt!$G$4:$G$33)) | D6: =IF($A6="","",SUMIF(Gantt!$D$4:$D$33,$A6,Gantt!J$4:J$33)) | E6: =IF($A6="","",SUMIF(Gantt!$D$4:$D$33,$A6,Gantt!K$4:K$33)) | F6: =IF($A6="","",SUMIF(Gantt!$D$4:$D$33,$A6,Gantt!L$4:L$33)) | G6: =IF($A6="","",SUMIF(Gantt!$D$4:$D$33,$A6,Gantt!M$4:M$33)) | H6: =IF($A6="","",SUMIF(Gantt!$D$4:$D$33,$A6,Gantt!N$4:N$33)) | I6: =IF($A6="","",SUMIF(Gantt!$D$4:$D$33,$A6,Gantt!O$4:O$33)) | J6: =IF($A6="","",SUMIF(Gantt!$D$4:$D$33,$A6,Gantt!P$4:P$33)) | K6: =IF($A6="","",SUMIF(Gantt!$D$4:$D$33,$A6,Gantt!Q$4:Q$33)) | ... U6: =IF($A6="","",SUMIF(Gantt!$D$4:$D$33,$A6,Gantt!AA$4:AA$33))
C7: =IF(A7="","",SUMIF(Gantt!$D$4:$D$33,A7,Gantt!$G$4:$G$33)) | D7: =IF($A7="","",SUMIF(Gantt!$D$4:$D$33,$A7,Gantt!J$4:J$33)) | E7: =IF($A7="","",SUMIF(Gantt!$D$4:$D$33,$A7,Gantt!K$4:K$33)) | F7: =IF($A7="","",SUMIF(Gantt!$D$4:$D$33,$A7,Gantt!L$4:L$33)) | G7: =IF($A7="","",SUMIF(Gantt!$D$4:$D$33,$A7,Gantt!M$4:M$33)) | H7: =IF($A7="","",SUMIF(Gantt!$D$4:$D$33,$A7,Gantt!N$4:N$33)) | I7: =IF($A7="","",SUMIF(Gantt!$D$4:$D$33,$A7,Gantt!O$4:O$33)) | J7: =IF($A7="","",SUMIF(Gantt!$D$4:$D$33,$A7,Gantt!P$4:P$33)) | K7: =IF($A7="","",SUMIF(Gantt!$D$4:$D$33,$A7,Gantt!Q$4:Q$33)) | ... U7: =IF($A7="","",SUMIF(Gantt!$D$4:$D$33,$A7,Gantt!AA$4:AA$33))
C8: =IF(A8="","",SUMIF(Gantt!$D$4:$D$33,A8,Gantt!$G$4:$G$33)) | D8: =IF($A8="","",SUMIF(Gantt!$D$4:$D$33,$A8,Gantt!J$4:J$33)) | E8: =IF($A8="","",SUMIF(Gantt!$D$4:$D$33,$A8,Gantt!K$4:K$33)) | F8: =IF($A8="","",SUMIF(Gantt!$D$4:$D$33,$A8,Gantt!L$4:L$33)) | G8: =IF($A8="","",SUMIF(Gantt!$D$4:$D$33,$A8,Gantt!M$4:M$33)) | H8: =IF($A8="","",SUMIF(Gantt!$D$4:$D$33,$A8,Gantt!N$4:N$33)) | I8: =IF($A8="","",SUMIF(Gantt!$D$4:$D$33,$A8,Gantt!O$4:O$33)) | J8: =IF($A8="","",SUMIF(Gantt!$D$4:$D$33,$A8,Gantt!P$4:P$33)) | K8: =IF($A8="","",SUMIF(Gantt!$D$4:$D$33,$A8,Gantt!Q$4:Q$33)) | ... U8: =IF($A8="","",SUMIF(Gantt!$D$4:$D$33,$A8,Gantt!AA$4:AA$33))
C9: =IF(A9="","",SUMIF(Gantt!$D$4:$D$33,A9,Gantt!$G$4:$G$33)) | D9: =IF($A9="","",SUMIF(Gantt!$D$4:$D$33,$A9,Gantt!J$4:J$33)) | E9: =IF($A9="","",SUMIF(Gantt!$D$4:$D$33,$A9,Gantt!K$4:K$33)) | F9: =IF($A9="","",SUMIF(Gantt!$D$4:$D$33,$A9,Gantt!L$4:L$33)) | G9: =IF($A9="","",SUMIF(Gantt!$D$4:$D$33,$A9,Gantt!M$4:M$33)) | H9: =IF($A9="","",SUMIF(Gantt!$D$4:$D$33,$A9,Gantt!N$4:N$33)) | I9: =IF($A9="","",SUMIF(Gantt!$D$4:$D$33,$A9,Gantt!O$4:O$33)) | J9: =IF($A9="","",SUMIF(Gantt!$D$4:$D$33,$A9,Gantt!P$4:P$33)) | K9: =IF($A9="","",SUMIF(Gantt!$D$4:$D$33,$A9,Gantt!Q$4:Q$33)) | ... U9: =IF($A9="","",SUMIF(Gantt!$D$4:$D$33,$A9,Gantt!AA$4:AA$33))
C10: =IF(A10="","",SUMIF(Gantt!$D$4:$D$33,A10,Gantt!$G$4:$G$33)) | D10: =IF($A10="","",SUMIF(Gantt!$D$4:$D$33,$A10,Gantt!J$4:J$33)) | E10: =IF($A10="","",SUMIF(Gantt!$D$4:$D$33,$A10,Gantt!K$4:K$33)) | F10: =IF($A10="","",SUMIF(Gantt!$D$4:$D$33,$A10,Gantt!L$4:L$33)) | G10: =IF($A10="","",SUMIF(Gantt!$D$4:$D$33,$A10,Gantt!M$4:M$33)) | H10: =IF($A10="","",SUMIF(Gantt!$D$4:$D$33,$A10,Gantt!N$4:N$33)) | I10: =IF($A10="","",SUMIF(Gantt!$D$4:$D$33,$A10,Gantt!O$4:O$33)) | J10: =IF($A10="","",SUMIF(Gantt!$D$4:$D$33,$A10,Gantt!P$4:P$33)) | K10: =IF($A10="","",SUMIF(Gantt!$D$4:$D$33,$A10,Gantt!Q$4:Q$33)) | ... U10: =IF($A10="","",SUMIF(Gantt!$D$4:$D$33,$A10,Gantt!AA$4:AA$33))
C11: =IF(A11="","",SUMIF(Gantt!$D$4:$D$33,A11,Gantt!$G$4:$G$33)) | D11: =IF($A11="","",SUMIF(Gantt!$D$4:$D$33,$A11,Gantt!J$4:J$33)) | E11: =IF($A11="","",SUMIF(Gantt!$D$4:$D$33,$A11,Gantt!K$4:K$33)) | F11: =IF($A11="","",SUMIF(Gantt!$D$4:$D$33,$A11,Gantt!L$4:L$33)) | G11: =IF($A11="","",SUMIF(Gantt!$D$4:$D$33,$A11,Gantt!M$4:M$33)) | H11: =IF($A11="","",SUMIF(Gantt!$D$4:$D$33,$A11,Gantt!N$4:N$33)) | I11: =IF($A11="","",SUMIF(Gantt!$D$4:$D$33,$A11,Gantt!O$4:O$33)) | J11: =IF($A11="","",SUMIF(Gantt!$D$4:$D$33,$A11,Gantt!P$4:P$33)) | K11: =IF($A11="","",SUMIF(Gantt!$D$4:$D$33,$A11,Gantt!Q$4:Q$33)) | ... U11: =IF($A11="","",SUMIF(Gantt!$D$4:$D$33,$A11,Gantt!AA$4:AA$33))
C12: =IF(A12="","",SUMIF(Gantt!$D$4:$D$33,A12,Gantt!$G$4:$G$33)) | D12: =IF($A12="","",SUMIF(Gantt!$D$4:$D$33,$A12,Gantt!J$4:J$33)) | E12: =IF($A12="","",SUMIF(Gantt!$D$4:$D$33,$A12,Gantt!K$4:K$33)) | F12: =IF($A12="","",SUMIF(Gantt!$D$4:$D$33,$A12,Gantt!L$4:L$33)) | G12: =IF($A12="","",SUMIF(Gantt!$D$4:$D$33,$A12,Gantt!M$4:M$33)) | H12: =IF($A12="","",SUMIF(Gantt!$D$4:$D$33,$A12,Gantt!N$4:N$33)) | I12: =IF($A12="","",SUMIF(Gantt!$D$4:$D$33,$A12,Gantt!O$4:O$33)) | J12: =IF($A12="","",SUMIF(Gantt!$D$4:$D$33,$A12,Gantt!P$4:P$33)) | K12: =IF($A12="","",SUMIF(Gantt!$D$4:$D$33,$A12,Gantt!Q$4:Q$33)) | ... U12: =IF($A12="","",SUMIF(Gantt!$D$4:$D$33,$A12,Gantt!AA$4:AA$33))
C13: =IF(A13="","",SUMIF(Gantt!$D$4:$D$33,A13,Gantt!$G$4:$G$33)) | D13: =IF($A13="","",SUMIF(Gantt!$D$4:$D$33,$A13,Gantt!J$4:J$33)) | E13: =IF($A13="","",SUMIF(Gantt!$D$4:$D$33,$A13,Gantt!K$4:K$33)) | F13: =IF($A13="","",SUMIF(Gantt!$D$4:$D$33,$A13,Gantt!L$4:L$33)) | G13: =IF($A13="","",SUMIF(Gantt!$D$4:$D$33,$A13,Gantt!M$4:M$33)) | H13: =IF($A13="","",SUMIF(Gantt!$D$4:$D$33,$A13,Gantt!N$4:N$33)) | I13: =IF($A13="","",SUMIF(Gantt!$D$4:$D$33,$A13,Gantt!O$4:O$33)) | J13: =IF($A13="","",SUMIF(Gantt!$D$4:$D$33,$A13,Gantt!P$4:P$33)) | K13: =IF($A13="","",SUMIF(Gantt!$D$4:$D$33,$A13,Gantt!Q$4:Q$33)) | ... U13: =IF($A13="","",SUMIF(Gantt!$D$4:$D$33,$A13,Gantt!AA$4:AA$33))
C14: =IF(A14="","",SUMIF(Gantt!$D$4:$D$33,A14,Gantt!$G$4:$G$33)) | D14: =IF($A14="","",SUMIF(Gantt!$D$4:$D$33,$A14,Gantt!J$4:J$33)) | E14: =IF($A14="","",SUMIF(Gantt!$D$4:$D$33,$A14,Gantt!K$4:K$33)) | F14: =IF($A14="","",SUMIF(Gantt!$D$4:$D$33,$A14,Gantt!L$4:L$33)) | G14: =IF($A14="","",SUMIF(Gantt!$D$4:$D$33,$A14,Gantt!M$4:M$33)) | H14: =IF($A14="","",SUMIF(Gantt!$D$4:$D$33,$A14,Gantt!N$4:N$33)) | I14: =IF($A14="","",SUMIF(Gantt!$D$4:$D$33,$A14,Gantt!O$4:O$33)) | J14: =IF($A14="","",SUMIF(Gantt!$D$4:$D$33,$A14,Gantt!P$4:P$33)) | K14: =IF($A14="","",SUMIF(Gantt!$D$4:$D$33,$A14,Gantt!Q$4:Q$33)) | ... U14: =IF($A14="","",SUMIF(Gantt!$D$4:$D$33,$A14,Gantt!AA$4:AA$33))
C15: =IF(A15="","",SUMIF(Gantt!$D$4:$D$33,A15,Gantt!$G$4:$G$33)) | D15: =IF($A15="","",SUMIF(Gantt!$D$4:$D$33,$A15,Gantt!J$4:J$33)) | E15: =IF($A15="","",SUMIF(Gantt!$D$4:$D$33,$A15,Gantt!K$4:K$33)) | F15: =IF($A15="","",SUMIF(Gantt!$D$4:$D$33,$A15,Gantt!L$4:L$33)) | G15: =IF($A15="","",SUMIF(Gantt!$D$4:$D$33,$A15,Gantt!M$4:M$33)) | H15: =IF($A15="","",SUMIF(Gantt!$D$4:$D$33,$A15,Gantt!N$4:N$33)) | I15: =IF($A15="","",SUMIF(Gantt!$D$4:$D$33,$A15,Gantt!O$4:O$33)) | J15: =IF($A15="","",SUMIF(Gantt!$D$4:$D$33,$A15,Gantt!P$4:P$33)) | K15: =IF($A15="","",SUMIF(Gantt!$D$4:$D$33,$A15,Gantt!Q$4:Q$33)) | ... U15: =IF($A15="","",SUMIF(Gantt!$D$4:$D$33,$A15,Gantt!AA$4:AA$33))
C16: =IF(A16="","",SUMIF(Gantt!$D$4:$D$33,A16,Gantt!$G$4:$G$33)) | D16: =IF($A16="","",SUMIF(Gantt!$D$4:$D$33,$A16,Gantt!J$4:J$33)) | E16: =IF($A16="","",SUMIF(Gantt!$D$4:$D$33,$A16,Gantt!K$4:K$33)) | F16: =IF($A16="","",SUMIF(Gantt!$D$4:$D$33,$A16,Gantt!L$4:L$33)) | G16: =IF($A16="","",SUMIF(Gantt!$D$4:$D$33,$A16,Gantt!M$4:M$33)) | H16: =IF($A16="","",SUMIF(Gantt!$D$4:$D$33,$A16,Gantt!N$4:N$33)) | I16: =IF($A16="","",SUMIF(Gantt!$D$4:$D$33,$A16,Gantt!O$4:O$33)) | J16: =IF($A16="","",SUMIF(Gantt!$D$4:$D$33,$A16,Gantt!P$4:P$33)) | K16: =IF($A16="","",SUMIF(Gantt!$D$4:$D$33,$A16,Gantt!Q$4:Q$33)) | ... U16: =IF($A16="","",SUMIF(Gantt!$D$4:$D$33,$A16,Gantt!AA$4:AA$33))
C17: =IF(A17="","",SUMIF(Gantt!$D$4:$D$33,A17,Gantt!$G$4:$G$33)) | D17: =IF($A17="","",SUMIF(Gantt!$D$4:$D$33,$A17,Gantt!J$4:J$33)) | E17: =IF($A17="","",SUMIF(Gantt!$D$4:$D$33,$A17,Gantt!K$4:K$33)) | F17: =IF($A17="","",SUMIF(Gantt!$D$4:$D$33,$A17,Gantt!L$4:L$33)) | G17: =IF($A17="","",SUMIF(Gantt!$D$4:$D$33,$A17,Gantt!M$4:M$33)) | H17: =IF($A17="","",SUMIF(Gantt!$D$4:$D$33,$A17,Gantt!N$4:N$33)) | I17: =IF($A17="","",SUMIF(Gantt!$D$4:$D$33,$A17,Gantt!O$4:O$33)) | J17: =IF($A17="","",SUMIF(Gantt!$D$4:$D$33,$A17,Gantt!P$4:P$33)) | K17: =IF($A17="","",SUMIF(Gantt!$D$4:$D$33,$A17,Gantt!Q$4:Q$33)) | ... U17: =IF($A17="","",SUMIF(Gantt!$D$4:$D$33,$A17,Gantt!AA$4:AA$33))
... C23: =IF(A23="","",SUMIF(Gantt!$D$4:$D$33,A23,Gantt!$G$4:$G$33)) | D23: =IF($A23="","",SUMIF(Gantt!$D$4:$D$33,$A23,Gantt!J$4:J$33)) | E23: =IF($A23="","",SUMIF(Gantt!$D$4:$D$33,$A23,Gantt!K$4:K$33)) | F23: =IF($A23="","",SUMIF(Gantt!$D$4:$D$33,$A23,Gantt!L$4:L$33)) | G23: =IF($A23="","",SUMIF(Gantt!$D$4:$D$33,$A23,Gantt!M$4:M$33)) | H23: =IF($A23="","",SUMIF(Gantt!$D$4:$D$33,$A23,Gantt!N$4:N$33)) | I23: =IF($A23="","",SUMIF(Gantt!$D$4:$D$33,$A23,Gantt!O$4:O$33)) | J23: =IF($A23="","",SUMIF(Gantt!$D$4:$D$33,$A23,Gantt!P$4:P$33)) | K23: =IF($A23="","",SUMIF(Gantt!$D$4:$D$33,$A23,Gantt!Q$4:Q$33)) | ... U23: =IF($A23="","",SUMIF(Gantt!$D$4:$D$33,$A23,Gantt!AA$4:AA$33))
A24: TOTAL affecté | C24: =SUM(C4:C23) -> 1620 | D24: =SUM(D4:D23) -> 80 | E24: =SUM(E4:E23) -> 320 | F24: =SUM(F4:F23) -> 320 | G24: =SUM(G4:G23) -> 320 | H24: =SUM(H4:H23) -> 320 | I24: =SUM(I4:I23) -> 260 | J24: =SUM(J4:J23) -> 0 | ... U24: =SUM(U4:U23) -> 0
A25: Non affecté | C25: =SUMIF(Gantt!$D$4:$D$33,"",Gantt!$G$4:$G$33) -> 0
A27: Ajouter une personne = écrire son nom sur une ligne libre (colonne A) ; elle apparaît aussitôt dans les listes « Responsable ». Rouge = plus de 160 h dans le mois.

Sheet Projets
A1: Projets
A3: Projet | B3: Client / maîtrise d'ouvrage | C3: Statut | D3: Tâches | E3: Charge (h) | F3: Réalisé (h) | G3: % réalisé
A4: Projet A | B4: Interne R&D | C4: En cours | D4: =IF($A4="","",COUNTIF(Gantt!$B$4:$B$33,$A4)) -> 3 | E4: =IF($A4="","",SUMIF(Gantt!$B$4:$B$33,$A4,Gantt!$G$4:$G$33)) -> 640 | F4: =IF($A4="","",SUMIFS(Gantt!$G$4:$G$33,Gantt!$B$4:$B$33,$A4,Gantt!$E$4:$E$33,"Réalisé")) -> 0 | G4: =IF(OR($A4="",N(E4)=0),"",F4/E4) -> 0
A5: Projet B | B5: Client A | C5: En cours | D5: =IF($A5="","",COUNTIF(Gantt!$B$4:$B$33,$A5)) -> 2 | E5: =IF($A5="","",SUMIF(Gantt!$B$4:$B$33,$A5,Gantt!$G$4:$G$33)) -> 980 | F5: =IF($A5="","",SUMIFS(Gantt!$G$4:$G$33,Gantt!$B$4:$B$33,$A5,Gantt!$E$4:$E$33,"Réalisé")) -> 0 | G5: =IF(OR($A5="",N(E5)=0),"",F5/E5) -> 0
D6: =IF($A6="","",COUNTIF(Gantt!$B$4:$B$33,$A6)) | E6: =IF($A6="","",SUMIF(Gantt!$B$4:$B$33,$A6,Gantt!$G$4:$G$33)) | F6: =IF($A6="","",SUMIFS(Gantt!$G$4:$G$33,Gantt!$B$4:$B$33,$A6,Gantt!$E$4:$E$33,"Réalisé")) | G6: =IF(OR($A6="",N(E6)=0),"",F6/E6)
D7: =IF($A7="","",COUNTIF(Gantt!$B$4:$B$33,$A7)) | E7: =IF($A7="","",SUMIF(Gantt!$B$4:$B$33,$A7,Gantt!$G$4:$G$33)) | F7: =IF($A7="","",SUMIFS(Gantt!$G$4:$G$33,Gantt!$B$4:$B$33,$A7,Gantt!$E$4:$E$33,"Réalisé")) | G7: =IF(OR($A7="",N(E7)=0),"",F7/E7)
D8: =IF($A8="","",COUNTIF(Gantt!$B$4:$B$33,$A8)) | E8: =IF($A8="","",SUMIF(Gantt!$B$4:$B$33,$A8,Gantt!$G$4:$G$33)) | F8: =IF($A8="","",SUMIFS(Gantt!$G$4:$G$33,Gantt!$B$4:$B$33,$A8,Gantt!$E$4:$E$33,"Réalisé")) | G8: =IF(OR($A8="",N(E8)=0),"",F8/E8)
D9: =IF($A9="","",COUNTIF(Gantt!$B$4:$B$33,$A9)) | E9: =IF($A9="","",SUMIF(Gantt!$B$4:$B$33,$A9,Gantt!$G$4:$G$33)) | F9: =IF($A9="","",SUMIFS(Gantt!$G$4:$G$33,Gantt!$B$4:$B$33,$A9,Gantt!$E$4:$E$33,"Réalisé")) | G9: =IF(OR($A9="",N(E9)=0),"",F9/E9)
D10: =IF($A10="","",COUNTIF(Gantt!$B$4:$B$33,$A10)) | E10: =IF($A10="","",SUMIF(Gantt!$B$4:$B$33,$A10,Gantt!$G$4:$G$33)) | F10: =IF($A10="","",SUMIFS(Gantt!$G$4:$G$33,Gantt!$B$4:$B$33,$A10,Gantt!$E$4:$E$33,"Réalisé")) | G10: =IF(OR($A10="",N(E10)=0),"",F10/E10)
D11: =IF($A11="","",COUNTIF(Gantt!$B$4:$B$33,$A11)) | E11: =IF($A11="","",SUMIF(Gantt!$B$4:$B$33,$A11,Gantt!$G$4:$G$33)) | F11: =IF($A11="","",SUMIFS(Gantt!$G$4:$G$33,Gantt!$B$4:$B$33,$A11,Gantt!$E$4:$E$33,"Réalisé")) | G11: =IF(OR($A11="",N(E11)=0),"",F11/E11)
D12: =IF($A12="","",COUNTIF(Gantt!$B$4:$B$33,$A12)) | E12: =IF($A12="","",SUMIF(Gantt!$B$4:$B$33,$A12,Gantt!$G$4:$G$33)) | F12: =IF($A12="","",SUMIFS(Gantt!$G$4:$G$33,Gantt!$B$4:$B$33,$A12,Gantt!$E$4:$E$33,"Réalisé")) | G12: =IF(OR($A12="",N(E12)=0),"",F12/E12)
D13: =IF($A13="","",COUNTIF(Gantt!$B$4:$B$33,$A13)) | E13: =IF($A13="","",SUMIF(Gantt!$B$4:$B$33,$A13,Gantt!$G$4:$G$33)) | F13: =IF($A13="","",SUMIFS(Gantt!$G$4:$G$33,Gantt!$B$4:$B$33,$A13,Gantt!$E$4:$E$33,"Réalisé")) | G13: =IF(OR($A13="",N(E13)=0),"",F13/E13)
D14: =IF($A14="","",COUNTIF(Gantt!$B$4:$B$33,$A14)) | E14: =IF($A14="","",SUMIF(Gantt!$B$4:$B$33,$A14,Gantt!$G$4:$G$33)) | F14: =IF($A14="","",SUMIFS(Gantt!$G$4:$G$33,Gantt!$B$4:$B$33,$A14,Gantt!$E$4:$E$33,"Réalisé")) | G14: =IF(OR($A14="",N(E14)=0),"",F14/E14)
D15: =IF($A15="","",COUNTIF(Gantt!$B$4:$B$33,$A15)) | E15: =IF($A15="","",SUMIF(Gantt!$B$4:$B$33,$A15,Gantt!$G$4:$G$33)) | F15: =IF($A15="","",SUMIFS(Gantt!$G$4:$G$33,Gantt!$B$4:$B$33,$A15,Gantt!$E$4:$E$33,"Réalisé")) | G15: =IF(OR($A15="",N(E15)=0),"",F15/E15)
D16: =IF($A16="","",COUNTIF(Gantt!$B$4:$B$33,$A16)) | E16: =IF($A16="","",SUMIF(Gantt!$B$4:$B$33,$A16,Gantt!$G$4:$G$33)) | F16: =IF($A16="","",SUMIFS(Gantt!$G$4:$G$33,Gantt!$B$4:$B$33,$A16,Gantt!$E$4:$E$33,"Réalisé")) | G16: =IF(OR($A16="",N(E16)=0),"",F16/E16)
D17: =IF($A17="","",COUNTIF(Gantt!$B$4:$B$33,$A17)) | E17: =IF($A17="","",SUMIF(Gantt!$B$4:$B$33,$A17,Gantt!$G$4:$G$33)) | F17: =IF($A17="","",SUMIFS(Gantt!$G$4:$G$33,Gantt!$B$4:$B$33,$A17,Gantt!$E$4:$E$33,"Réalisé")) | G17: =IF(OR($A17="",N(E17)=0),"",F17/E17)
D18: =IF($A18="","",COUNTIF(Gantt!$B$4:$B$33,$A18)) | E18: =IF($A18="","",SUMIF(Gantt!$B$4:$B$33,$A18,Gantt!$G$4:$G$33)) | F18: =IF($A18="","",SUMIFS(Gantt!$G$4:$G$33,Gantt!$B$4:$B$33,$A18,Gantt!$E$4:$E$33,"Réalisé")) | G18: =IF(OR($A18="",N(E18)=0),"",F18/E18)
A19: TOTAL | D19: =SUM(D4:D18) -> 5 | E19: =SUM(E4:E18) -> 1620 | F19: =SUM(F4:F18) -> 0
A20: Sans projet | E20: =SUMIF(Gantt!$B$4:$B$33,"",Gantt!$G$4:$G$33) -> 0
A22: Saisir les projets en colonne A (cellules jaunes) : ils alimentent la liste « Projet » du planning. Le reste est calculé.

Sheet Financement
A1: Sources de financement
A3: Source | B3: Certitude | C3: Description | D3: Budget (h) | E3: Affecté (h) | F3: Écart | G3: % consommé
A4: Interne | B4: Confirmé | C4: Budget R&D interne | D4: 600 | E4: =IF($A4="","",SUMIF(Répartition!$B$4:$B$103,$A4,Répartition!$C$4:$C$103)) -> 320 | F4: =IF($A4="","",D4-E4) -> 280 | G4: =IF(OR($A4="",N(D4)=0),"",E4/D4) -> 0.53333333
A5: Client A | B5: Confirmé | C5: Tranche ferme contrat | D5: 900 | E5: =IF($A5="","",SUMIF(Répartition!$B$4:$B$103,$A5,Répartition!$C$4:$C$103)) -> 1020 | F5: =IF($A5="","",D5-E5) -> -120 | G5: =IF(OR($A5="",N(D5)=0),"",E5/D5) -> 1.1333333
A6: Subvention | B6: Pressenti | C6: Aide à l'innovation | D6: 300 | E6: =IF($A6="","",SUMIF(Répartition!$B$4:$B$103,$A6,Répartition!$C$4:$C$103)) -> 180 | F6: =IF($A6="","",D6-E6) -> 120 | G6: =IF(OR($A6="",N(D6)=0),"",E6/D6) -> 0.6
A7: Client B | B7: Option | C7: Tranche conditionnelle | D7: 400 | E7: =IF($A7="","",SUMIF(Répartition!$B$4:$B$103,$A7,Répartition!$C$4:$C$103)) -> 100 | F7: =IF($A7="","",D7-E7) -> 300 | G7: =IF(OR($A7="",N(D7)=0),"",E7/D7) -> 0.25
E8: =IF($A8="","",SUMIF(Répartition!$B$4:$B$103,$A8,Répartition!$C$4:$C$103)) | F8: =IF($A8="","",D8-E8) | G8: =IF(OR($A8="",N(D8)=0),"",E8/D8)
E9: =IF($A9="","",SUMIF(Répartition!$B$4:$B$103,$A9,Répartition!$C$4:$C$103)) | F9: =IF($A9="","",D9-E9) | G9: =IF(OR($A9="",N(D9)=0),"",E9/D9)
E10: =IF($A10="","",SUMIF(Répartition!$B$4:$B$103,$A10,Répartition!$C$4:$C$103)) | F10: =IF($A10="","",D10-E10) | G10: =IF(OR($A10="",N(D10)=0),"",E10/D10)
E11: =IF($A11="","",SUMIF(Répartition!$B$4:$B$103,$A11,Répartition!$C$4:$C$103)) | F11: =IF($A11="","",D11-E11) | G11: =IF(OR($A11="",N(D11)=0),"",E11/D11)
E12: =IF($A12="","",SUMIF(Répartition!$B$4:$B$103,$A12,Répartition!$C$4:$C$103)) | F12: =IF($A12="","",D12-E12) | G12: =IF(OR($A12="",N(D12)=0),"",E12/D12)
E13: =IF($A13="","",SUMIF(Répartition!$B$4:$B$103,$A13,Répartition!$C$4:$C$103)) | F13: =IF($A13="","",D13-E13) | G13: =IF(OR($A13="",N(D13)=0),"",E13/D13)
E14: =IF($A14="","",SUMIF(Répartition!$B$4:$B$103,$A14,Répartition!$C$4:$C$103)) | F14: =IF($A14="","",D14-E14) | G14: =IF(OR($A14="",N(D14)=0),"",E14/D14)
E15: =IF($A15="","",SUMIF(Répartition!$B$4:$B$103,$A15,Répartition!$C$4:$C$103)) | F15: =IF($A15="","",D15-E15) | G15: =IF(OR($A15="",N(D15)=0),"",E15/D15)
E16: =IF($A16="","",SUMIF(Répartition!$B$4:$B$103,$A16,Répartition!$C$4:$C$103)) | F16: =IF($A16="","",D16-E16) | G16: =IF(OR($A16="",N(D16)=0),"",E16/D16)
E17: =IF($A17="","",SUMIF(Répartition!$B$4:$B$103,$A17,Répartition!$C$4:$C$103)) | F17: =IF($A17="","",D17-E17) | G17: =IF(OR($A17="",N(D17)=0),"",E17/D17)
E18: =IF($A18="","",SUMIF(Répartition!$B$4:$B$103,$A18,Répartition!$C$4:$C$103)) | F18: =IF($A18="","",D18-E18) | G18: =IF(OR($A18="",N(D18)=0),"",E18/D18)
A19: TOTAL | D19: =SUM(D4:D18) -> 2200 | E19: =SUM(E4:E18) -> 1620 | F19: =SUM(F4:F18) -> 580
A20: Dont confirmé | D20: =SUMIF($B$4:$B$18,"Confirmé",$D$4:$D$18) -> 1500 | E20: =SUMIF($B$4:$B$18,"Confirmé",$E$4:$E$18) -> 1340
A21: Dont pressenti / option | D21: =SUMIF($B$4:$B$18,"<>Confirmé",$D$4:$D$18) -> 700 | E21: =SUMIF($B$4:$B$18,"<>Confirmé",$E$4:$E$18) -> 280
A22: Charge non couverte | E22: =SUM(Gantt!$G$4:$G$33)-E19 -> 0
A24: Saisir les sources en colonne A et leur budget en D : elles alimentent la liste « Source » de l'onglet Répartition. Affecté = heures qui leur sont attribuées dans cet onglet.

Sheet Répartition
A1: Répartition du financement (heures par tâche et par source)
A3: Tâche | B3: Source | C3: Heures | D3: Certitude | E3: Projet | F3: Charge tâche | G3: Reste à financer
A4: Conception d'actifs 3D | B4: Interne | C4: 120 | D4: =IF($B4="","",IFERROR(VLOOKUP($B4,Financement!$A$4:$B$18,2,FALSE()),"")) -> Confirmé | E4: =IF($A4="","",IFERROR(INDEX(Gantt!$B$4:$B$33,MATCH($A4,Gantt!$C$4:$C$33,0)),"")) -> Projet A | F4: =IF($A4="","",IFERROR(INDEX(Gantt!$G$4:$G$33,MATCH($A4,Gantt!$C$4:$C$33,0)),"")) -> 120 | G4: =IF($A4="","",F4-SUMIF($A$4:$A$103,$A4,$C$4:$C$103)) -> 0
A5: Modélisation système | B5: Interne | C5: 200 | D5: =IF($B5="","",IFERROR(VLOOKUP($B5,Financement!$A$4:$B$18,2,FALSE()),"")) -> Confirmé | E5: =IF($A5="","",IFERROR(INDEX(Gantt!$B$4:$B$33,MATCH($A5,Gantt!$C$4:$C$33,0)),"")) -> Projet A | F5: =IF($A5="","",IFERROR(INDEX(Gantt!$G$4:$G$33,MATCH($A5,Gantt!$C$4:$C$33,0)),"")) -> 200 | G5: =IF($A5="","",F5-SUMIF($A$4:$A$103,$A5,$C$4:$C$103)) -> 0
A6: Intégration technique | B6: Client A | C6: 300 | D6: =IF($B6="","",IFERROR(VLOOKUP($B6,Financement!$A$4:$B$18,2,FALSE()),"")) -> Confirmé | E6: =IF($A6="","",IFERROR(INDEX(Gantt!$B$4:$B$33,MATCH($A6,Gantt!$C$4:$C$33,0)),"")) -> Projet B | F6: =IF($A6="","",IFERROR(INDEX(Gantt!$G$4:$G$33,MATCH($A6,Gantt!$C$4:$C$33,0)),"")) -> 480 | G6: =IF($A6="","",F6-SUMIF($A$4:$A$103,$A6,$C$4:$C$103)) -> 0
A7: Intégration technique | B7: Subvention | C7: 180 | D7: =IF($B7="","",IFERROR(VLOOKUP($B7,Financement!$A$4:$B$18,2,FALSE()),"")) -> Pressenti | E7: =IF($A7="","",IFERROR(INDEX(Gantt!$B$4:$B$33,MATCH($A7,Gantt!$C$4:$C$33,0)),"")) -> Projet B | F7: =IF($A7="","",IFERROR(INDEX(Gantt!$G$4:$G$33,MATCH($A7,Gantt!$C$4:$C$33,0)),"")) -> 480 | G7: =IF($A7="","",F7-SUMIF($A$4:$A$103,$A7,$C$4:$C$103)) -> 0
A8: Configuration scénarios | B8: Client A | C8: 500 | D8: =IF($B8="","",IFERROR(VLOOKUP($B8,Financement!$A$4:$B$18,2,FALSE()),"")) -> Confirmé | E8: =IF($A8="","",IFERROR(INDEX(Gantt!$B$4:$B$33,MATCH($A8,Gantt!$C$4:$C$33,0)),"")) -> Projet B | F8: =IF($A8="","",IFERROR(INDEX(Gantt!$G$4:$G$33,MATCH($A8,Gantt!$C$4:$C$33,0)),"")) -> 500 | G8: =IF($A8="","",F8-SUMIF($A$4:$A$103,$A8,$C$4:$C$103)) -> 0
A9: Préparation livraison | B9: Client A | C9: 220 | D9: =IF($B9="","",IFERROR(VLOOKUP($B9,Financement!$A$4:$B$18,2,FALSE()),"")) -> Confirmé | E9: =IF($A9="","",IFERROR(INDEX(Gantt!$B$4:$B$33,MATCH($A9,Gantt!$C$4:$C$33,0)),"")) -> Projet A | F9: =IF($A9="","",IFERROR(INDEX(Gantt!$G$4:$G$33,MATCH($A9,Gantt!$C$4:$C$33,0)),"")) -> 320 | G9: =IF($A9="","",F9-SUMIF($A$4:$A$103,$A9,$C$4:$C$103)) -> 0
A10: Préparation livraison | B10: Client B | C10: 100 | D10: =IF($B10="","",IFERROR(VLOOKUP($B10,Financement!$A$4:$B$18,2,FALSE()),"")) -> Option | E10: =IF($A10="","",IFERROR(INDEX(Gantt!$B$4:$B$33,MATCH($A10,Gantt!$C$4:$C$33,0)),"")) -> Projet A | F10: =IF($A10="","",IFERROR(INDEX(Gantt!$G$4:$G$33,MATCH($A10,Gantt!$C$4:$C$33,0)),"")) -> 320 | G10: =IF($A10="","",F10-SUMIF($A$4:$A$103,$A10,$C$4:$C$103)) -> 0
D11: =IF($B11="","",IFERROR(VLOOKUP($B11,Financement!$A$4:$B$18,2,FALSE()),"")) | E11: =IF($A11="","",IFERROR(INDEX(Gantt!$B$4:$B$33,MATCH($A11,Gantt!$C$4:$C$33,0)),"")) | F11: =IF($A11="","",IFERROR(INDEX(Gantt!$G$4:$G$33,MATCH($A11,Gantt!$C$4:$C$33,0)),"")) | G11: =IF($A11="","",F11-SUMIF($A$4:$A$103,$A11,$C$4:$C$103))
D12: =IF($B12="","",IFERROR(VLOOKUP($B12,Financement!$A$4:$B$18,2,FALSE()),"")) | E12: =IF($A12="","",IFERROR(INDEX(Gantt!$B$4:$B$33,MATCH($A12,Gantt!$C$4:$C$33,0)),"")) | F12: =IF($A12="","",IFERROR(INDEX(Gantt!$G$4:$G$33,MATCH($A12,Gantt!$C$4:$C$33,0)),"")) | G12: =IF($A12="","",F12-SUMIF($A$4:$A$103,$A12,$C$4:$C$103))
D13: =IF($B13="","",IFERROR(VLOOKUP($B13,Financement!$A$4:$B$18,2,FALSE()),"")) | E13: =IF($A13="","",IFERROR(INDEX(Gantt!$B$4:$B$33,MATCH($A13,Gantt!$C$4:$C$33,0)),"")) | F13: =IF($A13="","",IFERROR(INDEX(Gantt!$G$4:$G$33,MATCH($A13,Gantt!$C$4:$C$33,0)),"")) | G13: =IF($A13="","",F13-SUMIF($A$4:$A$103,$A13,$C$4:$C$103))
D14: =IF($B14="","",IFERROR(VLOOKUP($B14,Financement!$A$4:$B$18,2,FALSE()),"")) | E14: =IF($A14="","",IFERROR(INDEX(Gantt!$B$4:$B$33,MATCH($A14,Gantt!$C$4:$C$33,0)),"")) | F14: =IF($A14="","",IFERROR(INDEX(Gantt!$G$4:$G$33,MATCH($A14,Gantt!$C$4:$C$33,0)),"")) | G14: =IF($A14="","",F14-SUMIF($A$4:$A$103,$A14,$C$4:$C$103))
D15: =IF($B15="","",IFERROR(VLOOKUP($B15,Financement!$A$4:$B$18,2,FALSE()),"")) | E15: =IF($A15="","",IFERROR(INDEX(Gantt!$B$4:$B$33,MATCH($A15,Gantt!$C$4:$C$33,0)),"")) | F15: =IF($A15="","",IFERROR(INDEX(Gantt!$G$4:$G$33,MATCH($A15,Gantt!$C$4:$C$33,0)),"")) | G15: =IF($A15="","",F15-SUMIF($A$4:$A$103,$A15,$C$4:$C$103))
D16: =IF($B16="","",IFERROR(VLOOKUP($B16,Financement!$A$4:$B$18,2,FALSE()),"")) | E16: =IF($A16="","",IFERROR(INDEX(Gantt!$B$4:$B$33,MATCH($A16,Gantt!$C$4:$C$33,0)),"")) | F16: =IF($A16="","",IFERROR(INDEX(Gantt!$G$4:$G$33,MATCH($A16,Gantt!$C$4:$C$33,0)),"")) | G16: =IF($A16="","",F16-SUMIF($A$4:$A$103,$A16,$C$4:$C$103))
D17: =IF($B17="","",IFERROR(VLOOKUP($B17,Financement!$A$4:$B$18,2,FALSE()),"")) | E17: =IF($A17="","",IFERROR(INDEX(Gantt!$B$4:$B$33,MATCH($A17,Gantt!$C$4:$C$33,0)),"")) | F17: =IF($A17="","",IFERROR(INDEX(Gantt!$G$4:$G$33,MATCH($A17,Gantt!$C$4:$C$33,0)),"")) | G17: =IF($A17="","",F17-SUMIF($A$4:$A$103,$A17,$C$4:$C$103))
D18: =IF($B18="","",IFERROR(VLOOKUP($B18,Financement!$A$4:$B$18,2,FALSE()),"")) | E18: =IF($A18="","",IFERROR(INDEX(Gantt!$B$4:$B$33,MATCH($A18,Gantt!$C$4:$C$33,0)),"")) | F18: =IF($A18="","",IFERROR(INDEX(Gantt!$G$4:$G$33,MATCH($A18,Gantt!$C$4:$C$33,0)),"")) | G18: =IF($A18="","",F18-SUMIF($A$4:$A$103,$A18,$C$4:$C$103))
D19: =IF($B19="","",IFERROR(VLOOKUP($B19,Financement!$A$4:$B$18,2,FALSE()),"")) | E19: =IF($A19="","",IFERROR(INDEX(Gantt!$B$4:$B$33,MATCH($A19,Gantt!$C$4:$C$33,0)),"")) | F19: =IF($A19="","",IFERROR(INDEX(Gantt!$G$4:$G$33,MATCH($A19,Gantt!$C$4:$C$33,0)),"")) | G19: =IF($A19="","",F19-SUMIF($A$4:$A$103,$A19,$C$4:$C$103))
D20: =IF($B20="","",IFERROR(VLOOKUP($B20,Financement!$A$4:$B$18,2,FALSE()),"")) | E20: =IF($A20="","",IFERROR(INDEX(Gantt!$B$4:$B$33,MATCH($A20,Gantt!$C$4:$C$33,0)),"")) | F20: =IF($A20="","",IFERROR(INDEX(Gantt!$G$4:$G$33,MATCH($A20,Gantt!$C$4:$C$33,0)),"")) | G20: =IF($A20="","",F20-SUMIF($A$4:$A$103,$A20,$C$4:$C$103))
D21: =IF($B21="","",IFERROR(VLOOKUP($B21,Financement!$A$4:$B$18,2,FALSE()),"")) | E21: =IF($A21="","",IFERROR(INDEX(Gantt!$B$4:$B$33,MATCH($A21,Gantt!$C$4:$C$33,0)),"")) | F21: =IF($A21="","",IFERROR(INDEX(Gantt!$G$4:$G$33,MATCH($A21,Gantt!$C$4:$C$33,0)),"")) | G21: =IF($A21="","",F21-SUMIF($A$4:$A$103,$A21,$C$4:$C$103))
D22: =IF($B22="","",IFERROR(VLOOKUP($B22,Financement!$A$4:$B$18,2,FALSE()),"")) | E22: =IF($A22="","",IFERROR(INDEX(Gantt!$B$4:$B$33,MATCH($A22,Gantt!$C$4:$C$33,0)),"")) | F22: =IF($A22="","",IFERROR(INDEX(Gantt!$G$4:$G$33,MATCH($A22,Gantt!$C$4:$C$33,0)),"")) | G22: =IF($A22="","",F22-SUMIF($A$4:$A$103,$A22,$C$4:$C$103))
... D103: =IF($B103="","",IFERROR(VLOOKUP($B103,Financement!$A$4:$B$18,2,FALSE()),"")) | E103: =IF($A103="","",IFERROR(INDEX(Gantt!$B$4:$B$33,MATCH($A103,Gantt!$C$4:$C$33,0)),"")) | F103: =IF($A103="","",IFERROR(INDEX(Gantt!$G$4:$G$33,MATCH($A103,Gantt!$C$4:$C$33,0)),"")) | G103: =IF($A103="","",F103-SUMIF($A$4:$A$103,$A103,$C$4:$C$103))
A104: TOTAL | C104: =SUM(C4:C103) -> 1620
A106: Une ligne = une part de financement. Répéter la même tâche sur plusieurs lignes pour la partager entre sources. Reste à financer : vert = couverte, orange = incomplète, rouge = sur-financée.

Sheet Pointage
A1: Pointage des heures consommées
A2: Une ligne = un pointage. Saisir la date, la personne, la tâche, la source de financement et les heures réalisées. Projet et mois sont déduits. Les synthèses à droite comparent budget, prévu et pointé.
A3: Date | B3: Personne | C3: Tâche | D3: Projet | E3: Source | F3: Heures | G3: Mois | H3: Commentaire | J3: Source | K3: Budget (h) | L3: Prévu (h) | M3: Pointé (h) | N3: Reste budget | O3: % consommé | Q3: Tâche | R3: Projet | S3: Charge prévue | T3: Pointé (h) | U3: Écart | V3: % avancement réel
A4: 46280 | B4: Personne A | C4: Conception d'actifs 3D | D4: =IF($C4="","",IFERROR(INDEX(Gantt!$B$4:$B$33,MATCH($C4,Gantt!$C$4:$C$33,0)),"")) -> Projet A | E4: Interne | F4: 45 | G4: =IF($A4="","",DATE(YEAR($A4),MONTH($A4),1)) -> 46266 | H4: Blocking des assets | J4: =IF(Financement!$A4="","",Financement!$A4) -> Interne | K4: =IF($J4="","",Financement!$D4) -> 600 | L4: =IF($J4="","",Financement!$E4) -> 320 | M4: =IF($J4="","",SUMIF($E$4:$E$303,$J4,$F$4:$F$303)) -> 83 | N4: =IF($J4="","",K4-M4) -> 517 | O4: =IF(OR($J4="",N(K4)=0),"",M4/K4) -> 0.13833333 | Q4: =IF(Gantt!$C4="","",Gantt!$C4) -> Conception d'actifs 3D | R4: =IF($Q4="","",Gantt!$B4) -> Projet A | S4: =IF($Q4="","",Gantt!$G4) -> 120 | T4: =IF($Q4="","",SUMIF($C$4:$C$303,$Q4,$F$4:$F$303)) -> 83 | U4: =IF($Q4="","",S4-T4) -> 37 | V4: =IF(OR($Q4="",N(S4)=0),"",T4/S4) -> 0.69166667
A5: 46294 | B5: Personne A | C5: Conception d'actifs 3D | D5: =IF($C5="","",IFERROR(INDEX(Gantt!$B$4:$B$33,MATCH($C5,Gantt!$C$4:$C$33,0)),"")) -> Projet A | E5: Interne | F5: 38 | G5: =IF($A5="","",DATE(YEAR($A5),MONTH($A5),1)) -> 46266 | H5: Textures | J5: =IF(Financement!$A5="","",Financement!$A5) -> Client A | K5: =IF($J5="","",Financement!$D5) -> 900 | L5: =IF($J5="","",Financement!$E5) -> 1020 | M5: =IF($J5="","",SUMIF($E$4:$E$303,$J5,$F$4:$F$303)) -> 60 | N5: =IF($J5="","",K5-M5) -> 840 | O5: =IF(OR($J5="",N(K5)=0),"",M5/K5) -> 0.066666667 | Q5: =IF(Gantt!$C5="","",Gantt!$C5) -> Modélisation système | R5: =IF($Q5="","",Gantt!$B5) -> Projet A | S5: =IF($Q5="","",Gantt!$G5) -> 200 | T5: =IF($Q5="","",SUMIF($C$4:$C$303,$Q5,$F$4:$F$303)) -> 0 | U5: =IF($Q5="","",S5-T5) -> 200 | V5: =IF(OR($Q5="",N(S5)=0),"",T5/S5) -> 0
A6: 46308 | B6: Personne B | C6: Intégration technique | D6: =IF($C6="","",IFERROR(INDEX(Gantt!$B$4:$B$33,MATCH($C6,Gantt!$C$4:$C$33,0)),"")) -> Projet B | E6: Client A | F6: 60 | G6: =IF($A6="","",DATE(YEAR($A6),MONTH($A6),1)) -> 46296 | H6: Bus de données | J6: =IF(Financement!$A6="","",Financement!$A6) -> Subvention | K6: =IF($J6="","",Financement!$D6) -> 300 | L6: =IF($J6="","",Financement!$E6) -> 180 | M6: =IF($J6="","",SUMIF($E$4:$E$303,$J6,$F$4:$F$303)) -> 0 | N6: =IF($J6="","",K6-M6) -> 300 | O6: =IF(OR($J6="",N(K6)=0),"",M6/K6) -> 0 | Q6: =IF(Gantt!$C6="","",Gantt!$C6) -> Intégration technique | R6: =IF($Q6="","",Gantt!$B6) -> Projet B | S6: =IF($Q6="","",Gantt!$G6) -> 480 | T6: =IF($Q6="","",SUMIF($C$4:$C$303,$Q6,$F$4:$F$303)) -> 60 | U6: =IF($Q6="","",S6-T6) -> 420 | V6: =IF(OR($Q6="",N(S6)=0),"",T6/S6) -> 0.125
D7: =IF($C7="","",IFERROR(INDEX(Gantt!$B$4:$B$33,MATCH($C7,Gantt!$C$4:$C$33,0)),"")) | G7: =IF($A7="","",DATE(YEAR($A7),MONTH($A7),1)) | J7: =IF(Financement!$A7="","",Financement!$A7) -> Client B | K7: =IF($J7="","",Financement!$D7) -> 400 | L7: =IF($J7="","",Financement!$E7) -> 100 | M7: =IF($J7="","",SUMIF($E$4:$E$303,$J7,$F$4:$F$303)) -> 0 | N7: =IF($J7="","",K7-M7) -> 400 | O7: =IF(OR($J7="",N(K7)=0),"",M7/K7) -> 0 | Q7: =IF(Gantt!$C7="","",Gantt!$C7) -> Configuration scénarios | R7: =IF($Q7="","",Gantt!$B7) -> Projet B | S7: =IF($Q7="","",Gantt!$G7) -> 500 | T7: =IF($Q7="","",SUMIF($C$4:$C$303,$Q7,$F$4:$F$303)) -> 0 | U7: =IF($Q7="","",S7-T7) -> 500 | V7: =IF(OR($Q7="",N(S7)=0),"",T7/S7) -> 0
D8: =IF($C8="","",IFERROR(INDEX(Gantt!$B$4:$B$33,MATCH($C8,Gantt!$C$4:$C$33,0)),"")) | G8: =IF($A8="","",DATE(YEAR($A8),MONTH($A8),1)) | J8: =IF(Financement!$A8="","",Financement!$A8) | K8: =IF($J8="","",Financement!$D8) | L8: =IF($J8="","",Financement!$E8) | M8: =IF($J8="","",SUMIF($E$4:$E$303,$J8,$F$4:$F$303)) | N8: =IF($J8="","",K8-M8) | O8: =IF(OR($J8="",N(K8)=0),"",M8/K8) | Q8: =IF(Gantt!$C8="","",Gantt!$C8) -> Préparation livraison | R8: =IF($Q8="","",Gantt!$B8) -> Projet A | S8: =IF($Q8="","",Gantt!$G8) -> 320 | T8: =IF($Q8="","",SUMIF($C$4:$C$303,$Q8,$F$4:$F$303)) -> 0 | U8: =IF($Q8="","",S8-T8) -> 320 | V8: =IF(OR($Q8="",N(S8)=0),"",T8/S8) -> 0
D9: =IF($C9="","",IFERROR(INDEX(Gantt!$B$4:$B$33,MATCH($C9,Gantt!$C$4:$C$33,0)),"")) | G9: =IF($A9="","",DATE(YEAR($A9),MONTH($A9),1)) | J9: =IF(Financement!$A9="","",Financement!$A9) | K9: =IF($J9="","",Financement!$D9) | L9: =IF($J9="","",Financement!$E9) | M9: =IF($J9="","",SUMIF($E$4:$E$303,$J9,$F$4:$F$303)) | N9: =IF($J9="","",K9-M9) | O9: =IF(OR($J9="",N(K9)=0),"",M9/K9) | Q9: =IF(Gantt!$C9="","",Gantt!$C9) | R9: =IF($Q9="","",Gantt!$B9) | S9: =IF($Q9="","",Gantt!$G9) | T9: =IF($Q9="","",SUMIF($C$4:$C$303,$Q9,$F$4:$F$303)) | U9: =IF($Q9="","",S9-T9) | V9: =IF(OR($Q9="",N(S9)=0),"",T9/S9)
D10: =IF($C10="","",IFERROR(INDEX(Gantt!$B$4:$B$33,MATCH($C10,Gantt!$C$4:$C$33,0)),"")) | G10: =IF($A10="","",DATE(YEAR($A10),MONTH($A10),1)) | J10: =IF(Financement!$A10="","",Financement!$A10) | K10: =IF($J10="","",Financement!$D10) | L10: =IF($J10="","",Financement!$E10) | M10: =IF($J10="","",SUMIF($E$4:$E$303,$J10,$F$4:$F$303)) | N10: =IF($J10="","",K10-M10) | O10: =IF(OR($J10="",N(K10)=0),"",M10/K10) | Q10: =IF(Gantt!$C10="","",Gantt!$C10) | R10: =IF($Q10="","",Gantt!$B10) | S10: =IF($Q10="","",Gantt!$G10) | T10: =IF($Q10="","",SUMIF($C$4:$C$303,$Q10,$F$4:$F$303)) | U10: =IF($Q10="","",S10-T10) | V10: =IF(OR($Q10="",N(S10)=0),"",T10/S10)
D11: =IF($C11="","",IFERROR(INDEX(Gantt!$B$4:$B$33,MATCH($C11,Gantt!$C$4:$C$33,0)),"")) | G11: =IF($A11="","",DATE(YEAR($A11),MONTH($A11),1)) | J11: =IF(Financement!$A11="","",Financement!$A11) | K11: =IF($J11="","",Financement!$D11) | L11: =IF($J11="","",Financement!$E11) | M11: =IF($J11="","",SUMIF($E$4:$E$303,$J11,$F$4:$F$303)) | N11: =IF($J11="","",K11-M11) | O11: =IF(OR($J11="",N(K11)=0),"",M11/K11) | Q11: =IF(Gantt!$C11="","",Gantt!$C11) | R11: =IF($Q11="","",Gantt!$B11) | S11: =IF($Q11="","",Gantt!$G11) | T11: =IF($Q11="","",SUMIF($C$4:$C$303,$Q11,$F$4:$F$303)) | U11: =IF($Q11="","",S11-T11) | V11: =IF(OR($Q11="",N(S11)=0),"",T11/S11)
D12: =IF($C12="","",IFERROR(INDEX(Gantt!$B$4:$B$33,MATCH($C12,Gantt!$C$4:$C$33,0)),"")) | G12: =IF($A12="","",DATE(YEAR($A12),MONTH($A12),1)) | J12: =IF(Financement!$A12="","",Financement!$A12) | K12: =IF($J12="","",Financement!$D12) | L12: =IF($J12="","",Financement!$E12) | M12: =IF($J12="","",SUMIF($E$4:$E$303,$J12,$F$4:$F$303)) | N12: =IF($J12="","",K12-M12) | O12: =IF(OR($J12="",N(K12)=0),"",M12/K12) | Q12: =IF(Gantt!$C12="","",Gantt!$C12) | R12: =IF($Q12="","",Gantt!$B12) | S12: =IF($Q12="","",Gantt!$G12) | T12: =IF($Q12="","",SUMIF($C$4:$C$303,$Q12,$F$4:$F$303)) | U12: =IF($Q12="","",S12-T12) | V12: =IF(OR($Q12="",N(S12)=0),"",T12/S12)
D13: =IF($C13="","",IFERROR(INDEX(Gantt!$B$4:$B$33,MATCH($C13,Gantt!$C$4:$C$33,0)),"")) | G13: =IF($A13="","",DATE(YEAR($A13),MONTH($A13),1)) | J13: =IF(Financement!$A13="","",Financement!$A13) | K13: =IF($J13="","",Financement!$D13) | L13: =IF($J13="","",Financement!$E13) | M13: =IF($J13="","",SUMIF($E$4:$E$303,$J13,$F$4:$F$303)) | N13: =IF($J13="","",K13-M13) | O13: =IF(OR($J13="",N(K13)=0),"",M13/K13) | Q13: =IF(Gantt!$C13="","",Gantt!$C13) | R13: =IF($Q13="","",Gantt!$B13) | S13: =IF($Q13="","",Gantt!$G13) | T13: =IF($Q13="","",SUMIF($C$4:$C$303,$Q13,$F$4:$F$303)) | U13: =IF($Q13="","",S13-T13) | V13: =IF(OR($Q13="",N(S13)=0),"",T13/S13)
D14: =IF($C14="","",IFERROR(INDEX(Gantt!$B$4:$B$33,MATCH($C14,Gantt!$C$4:$C$33,0)),"")) | G14: =IF($A14="","",DATE(YEAR($A14),MONTH($A14),1)) | J14: =IF(Financement!$A14="","",Financement!$A14) | K14: =IF($J14="","",Financement!$D14) | L14: =IF($J14="","",Financement!$E14) | M14: =IF($J14="","",SUMIF($E$4:$E$303,$J14,$F$4:$F$303)) | N14: =IF($J14="","",K14-M14) | O14: =IF(OR($J14="",N(K14)=0),"",M14/K14) | Q14: =IF(Gantt!$C14="","",Gantt!$C14) | R14: =IF($Q14="","",Gantt!$B14) | S14: =IF($Q14="","",Gantt!$G14) | T14: =IF($Q14="","",SUMIF($C$4:$C$303,$Q14,$F$4:$F$303)) | U14: =IF($Q14="","",S14-T14) | V14: =IF(OR($Q14="",N(S14)=0),"",T14/S14)
D15: =IF($C15="","",IFERROR(INDEX(Gantt!$B$4:$B$33,MATCH($C15,Gantt!$C$4:$C$33,0)),"")) | G15: =IF($A15="","",DATE(YEAR($A15),MONTH($A15),1)) | J15: =IF(Financement!$A15="","",Financement!$A15) | K15: =IF($J15="","",Financement!$D15) | L15: =IF($J15="","",Financement!$E15) | M15: =IF($J15="","",SUMIF($E$4:$E$303,$J15,$F$4:$F$303)) | N15: =IF($J15="","",K15-M15) | O15: =IF(OR($J15="",N(K15)=0),"",M15/K15) | Q15: =IF(Gantt!$C15="","",Gantt!$C15) | R15: =IF($Q15="","",Gantt!$B15) | S15: =IF($Q15="","",Gantt!$G15) | T15: =IF($Q15="","",SUMIF($C$4:$C$303,$Q15,$F$4:$F$303)) | U15: =IF($Q15="","",S15-T15) | V15: =IF(OR($Q15="",N(S15)=0),"",T15/S15)
D16: =IF($C16="","",IFERROR(INDEX(Gantt!$B$4:$B$33,MATCH($C16,Gantt!$C$4:$C$33,0)),"")) | G16: =IF($A16="","",DATE(YEAR($A16),MONTH($A16),1)) | J16: =IF(Financement!$A16="","",Financement!$A16) | K16: =IF($J16="","",Financement!$D16) | L16: =IF($J16="","",Financement!$E16) | M16: =IF($J16="","",SUMIF($E$4:$E$303,$J16,$F$4:$F$303)) | N16: =IF($J16="","",K16-M16) | O16: =IF(OR($J16="",N(K16)=0),"",M16/K16) | Q16: =IF(Gantt!$C16="","",Gantt!$C16) | R16: =IF($Q16="","",Gantt!$B16) | S16: =IF($Q16="","",Gantt!$G16) | T16: =IF($Q16="","",SUMIF($C$4:$C$303,$Q16,$F$4:$F$303)) | U16: =IF($Q16="","",S16-T16) | V16: =IF(OR($Q16="",N(S16)=0),"",T16/S16)
D17: =IF($C17="","",IFERROR(INDEX(Gantt!$B$4:$B$33,MATCH($C17,Gantt!$C$4:$C$33,0)),"")) | G17: =IF($A17="","",DATE(YEAR($A17),MONTH($A17),1)) | J17: =IF(Financement!$A17="","",Financement!$A17) | K17: =IF($J17="","",Financement!$D17) | L17: =IF($J17="","",Financement!$E17) | M17: =IF($J17="","",SUMIF($E$4:$E$303,$J17,$F$4:$F$303)) | N17: =IF($J17="","",K17-M17) | O17: =IF(OR($J17="",N(K17)=0),"",M17/K17) | Q17: =IF(Gantt!$C17="","",Gantt!$C17) | R17: =IF($Q17="","",Gantt!$B17) | S17: =IF($Q17="","",Gantt!$G17) | T17: =IF($Q17="","",SUMIF($C$4:$C$303,$Q17,$F$4:$F$303)) | U17: =IF($Q17="","",S17-T17) | V17: =IF(OR($Q17="",N(S17)=0),"",T17/S17)
D18: =IF($C18="","",IFERROR(INDEX(Gantt!$B$4:$B$33,MATCH($C18,Gantt!$C$4:$C$33,0)),"")) | G18: =IF($A18="","",DATE(YEAR($A18),MONTH($A18),1)) | J18: =IF(Financement!$A18="","",Financement!$A18) | K18: =IF($J18="","",Financement!$D18) | L18: =IF($J18="","",Financement!$E18) | M18: =IF($J18="","",SUMIF($E$4:$E$303,$J18,$F$4:$F$303)) | N18: =IF($J18="","",K18-M18) | O18: =IF(OR($J18="",N(K18)=0),"",M18/K18) | Q18: =IF(Gantt!$C18="","",Gantt!$C18) | R18: =IF($Q18="","",Gantt!$B18) | S18: =IF($Q18="","",Gantt!$G18) | T18: =IF($Q18="","",SUMIF($C$4:$C$303,$Q18,$F$4:$F$303)) | U18: =IF($Q18="","",S18-T18) | V18: =IF(OR($Q18="",N(S18)=0),"",T18/S18)
D19: =IF($C19="","",IFERROR(INDEX(Gantt!$B$4:$B$33,MATCH($C19,Gantt!$C$4:$C$33,0)),"")) | G19: =IF($A19="","",DATE(YEAR($A19),MONTH($A19),1)) | J19: TOTAL | K19: =SUM(K4:K18) -> 2200 | L19: =SUM(L4:L18) -> 1620 | M19: =SUM(M4:M18) -> 143 | N19: =SUM(N4:N18) -> 2057 | Q19: =IF(Gantt!$C19="","",Gantt!$C19) | R19: =IF($Q19="","",Gantt!$B19) | S19: =IF($Q19="","",Gantt!$G19) | T19: =IF($Q19="","",SUMIF($C$4:$C$303,$Q19,$F$4:$F$303)) | U19: =IF($Q19="","",S19-T19) | V19: =IF(OR($Q19="",N(S19)=0),"",T19/S19)
D20: =IF($C20="","",IFERROR(INDEX(Gantt!$B$4:$B$33,MATCH($C20,Gantt!$C$4:$C$33,0)),"")) | G20: =IF($A20="","",DATE(YEAR($A20),MONTH($A20),1)) | J20: Pointé hors source | M20: =SUMIF($E$4:$E$303,"",$F$4:$F$303) -> 0 | Q20: =IF(Gantt!$C20="","",Gantt!$C20) | R20: =IF($Q20="","",Gantt!$B20) | S20: =IF($Q20="","",Gantt!$G20) | T20: =IF($Q20="","",SUMIF($C$4:$C$303,$Q20,$F$4:$F$303)) | U20: =IF($Q20="","",S20-T20) | V20: =IF(OR($Q20="",N(S20)=0),"",T20/S20)
D21: =IF($C21="","",IFERROR(INDEX(Gantt!$B$4:$B$33,MATCH($C21,Gantt!$C$4:$C$33,0)),"")) | G21: =IF($A21="","",DATE(YEAR($A21),MONTH($A21),1)) | J21: Pointé par personne | Q21: =IF(Gantt!$C21="","",Gantt!$C21) | R21: =IF($Q21="","",Gantt!$B21) | S21: =IF($Q21="","",Gantt!$G21) | T21: =IF($Q21="","",SUMIF($C$4:$C$303,$Q21,$F$4:$F$303)) | U21: =IF($Q21="","",S21-T21) | V21: =IF(OR($Q21="",N(S21)=0),"",T21/S21)
D22: =IF($C22="","",IFERROR(INDEX(Gantt!$B$4:$B$33,MATCH($C22,Gantt!$C$4:$C$33,0)),"")) | G22: =IF($A22="","",DATE(YEAR($A22),MONTH($A22),1)) | J22: Personne | K22: Prévu (h) | L22: Pointé (h) | M22: Écart | Q22: =IF(Gantt!$C22="","",Gantt!$C22) | R22: =IF($Q22="","",Gantt!$B22) | S22: =IF($Q22="","",Gantt!$G22) | T22: =IF($Q22="","",SUMIF($C$4:$C$303,$Q22,$F$4:$F$303)) | U22: =IF($Q22="","",S22-T22) | V22: =IF(OR($Q22="",N(S22)=0),"",T22/S22)
D23: =IF($C23="","",IFERROR(INDEX(Gantt!$B$4:$B$33,MATCH($C23,Gantt!$C$4:$C$33,0)),"")) | G23: =IF($A23="","",DATE(YEAR($A23),MONTH($A23),1)) | J23: =IF(Équipe!$A4="","",Équipe!$A4) -> Personne A | K23: =IF($J23="","",Équipe!$C4) -> 640 | L23: =IF($J23="","",SUMIF($B$4:$B$303,$J23,$F$4:$F$303)) -> 83 | M23: =IF($J23="","",K23-L23) -> 557 | Q23: =IF(Gantt!$C23="","",Gantt!$C23) | R23: =IF($Q23="","",Gantt!$B23) | S23: =IF($Q23="","",Gantt!$G23) | T23: =IF($Q23="","",SUMIF($C$4:$C$303,$Q23,$F$4:$F$303)) | U23: =IF($Q23="","",S23-T23) | V23: =IF(OR($Q23="",N(S23)=0),"",T23/S23)
D24: =IF($C24="","",IFERROR(INDEX(Gantt!$B$4:$B$33,MATCH($C24,Gantt!$C$4:$C$33,0)),"")) | G24: =IF($A24="","",DATE(YEAR($A24),MONTH($A24),1)) | J24: =IF(Équipe!$A5="","",Équipe!$A5) -> Personne B | K24: =IF($J24="","",Équipe!$C5) -> 980 | L24: =IF($J24="","",SUMIF($B$4:$B$303,$J24,$F$4:$F$303)) -> 60 | M24: =IF($J24="","",K24-L24) -> 920 | Q24: =IF(Gantt!$C24="","",Gantt!$C24) | R24: =IF($Q24="","",Gantt!$B24) | S24: =IF($Q24="","",Gantt!$G24) | T24: =IF($Q24="","",SUMIF($C$4:$C$303,$Q24,$F$4:$F$303)) | U24: =IF($Q24="","",S24-T24) | V24: =IF(OR($Q24="",N(S24)=0),"",T24/S24)
D25: =IF($C25="","",IFERROR(INDEX(Gantt!$B$4:$B$33,MATCH($C25,Gantt!$C$4:$C$33,0)),"")) | G25: =IF($A25="","",DATE(YEAR($A25),MONTH($A25),1)) | J25: =IF(Équipe!$A6="","",Équipe!$A6) | K25: =IF($J25="","",Équipe!$C6) | L25: =IF($J25="","",SUMIF($B$4:$B$303,$J25,$F$4:$F$303)) | M25: =IF($J25="","",K25-L25) | Q25: =IF(Gantt!$C25="","",Gantt!$C25) | R25: =IF($Q25="","",Gantt!$B25) | S25: =IF($Q25="","",Gantt!$G25) | T25: =IF($Q25="","",SUMIF($C$4:$C$303,$Q25,$F$4:$F$303)) | U25: =IF($Q25="","",S25-T25) | V25: =IF(OR($Q25="",N(S25)=0),"",T25/S25)
D26: =IF($C26="","",IFERROR(INDEX(Gantt!$B$4:$B$33,MATCH($C26,Gantt!$C$4:$C$33,0)),"")) | G26: =IF($A26="","",DATE(YEAR($A26),MONTH($A26),1)) | J26: =IF(Équipe!$A7="","",Équipe!$A7) | K26: =IF($J26="","",Équipe!$C7) | L26: =IF($J26="","",SUMIF($B$4:$B$303,$J26,$F$4:$F$303)) | M26: =IF($J26="","",K26-L26) | Q26: =IF(Gantt!$C26="","",Gantt!$C26) | R26: =IF($Q26="","",Gantt!$B26) | S26: =IF($Q26="","",Gantt!$G26) | T26: =IF($Q26="","",SUMIF($C$4:$C$303,$Q26,$F$4:$F$303)) | U26: =IF($Q26="","",S26-T26) | V26: =IF(OR($Q26="",N(S26)=0),"",T26/S26)
D27: =IF($C27="","",IFERROR(INDEX(Gantt!$B$4:$B$33,MATCH($C27,Gantt!$C$4:$C$33,0)),"")) | G27: =IF($A27="","",DATE(YEAR($A27),MONTH($A27),1)) | J27: =IF(Équipe!$A8="","",Équipe!$A8) | K27: =IF($J27="","",Équipe!$C8) | L27: =IF($J27="","",SUMIF($B$4:$B$303,$J27,$F$4:$F$303)) | M27: =IF($J27="","",K27-L27) | Q27: =IF(Gantt!$C27="","",Gantt!$C27) | R27: =IF($Q27="","",Gantt!$B27) | S27: =IF($Q27="","",Gantt!$G27) | T27: =IF($Q27="","",SUMIF($C$4:$C$303,$Q27,$F$4:$F$303)) | U27: =IF($Q27="","",S27-T27) | V27: =IF(OR($Q27="",N(S27)=0),"",T27/S27)
D28: =IF($C28="","",IFERROR(INDEX(Gantt!$B$4:$B$33,MATCH($C28,Gantt!$C$4:$C$33,0)),"")) | G28: =IF($A28="","",DATE(YEAR($A28),MONTH($A28),1)) | J28: =IF(Équipe!$A9="","",Équipe!$A9) | K28: =IF($J28="","",Équipe!$C9) | L28: =IF($J28="","",SUMIF($B$4:$B$303,$J28,$F$4:$F$303)) | M28: =IF($J28="","",K28-L28) | Q28: =IF(Gantt!$C28="","",Gantt!$C28) | R28: =IF($Q28="","",Gantt!$B28) | S28: =IF($Q28="","",Gantt!$G28) | T28: =IF($Q28="","",SUMIF($C$4:$C$303,$Q28,$F$4:$F$303)) | U28: =IF($Q28="","",S28-T28) | V28: =IF(OR($Q28="",N(S28)=0),"",T28/S28)
D29: =IF($C29="","",IFERROR(INDEX(Gantt!$B$4:$B$33,MATCH($C29,Gantt!$C$4:$C$33,0)),"")) | G29: =IF($A29="","",DATE(YEAR($A29),MONTH($A29),1)) | J29: =IF(Équipe!$A10="","",Équipe!$A10) | K29: =IF($J29="","",Équipe!$C10) | L29: =IF($J29="","",SUMIF($B$4:$B$303,$J29,$F$4:$F$303)) | M29: =IF($J29="","",K29-L29) | Q29: =IF(Gantt!$C29="","",Gantt!$C29) | R29: =IF($Q29="","",Gantt!$B29) | S29: =IF($Q29="","",Gantt!$G29) | T29: =IF($Q29="","",SUMIF($C$4:$C$303,$Q29,$F$4:$F$303)) | U29: =IF($Q29="","",S29-T29) | V29: =IF(OR($Q29="",N(S29)=0),"",T29/S29)
D30: =IF($C30="","",IFERROR(INDEX(Gantt!$B$4:$B$33,MATCH($C30,Gantt!$C$4:$C$33,0)),"")) | G30: =IF($A30="","",DATE(YEAR($A30),MONTH($A30),1)) | J30: =IF(Équipe!$A11="","",Équipe!$A11) | K30: =IF($J30="","",Équipe!$C11) | L30: =IF($J30="","",SUMIF($B$4:$B$303,$J30,$F$4:$F$303)) | M30: =IF($J30="","",K30-L30) | Q30: =IF(Gantt!$C30="","",Gantt!$C30) | R30: =IF($Q30="","",Gantt!$B30) | S30: =IF($Q30="","",Gantt!$G30) | T30: =IF($Q30="","",SUMIF($C$4:$C$303,$Q30,$F$4:$F$303)) | U30: =IF($Q30="","",S30-T30) | V30: =IF(OR($Q30="",N(S30)=0),"",T30/S30)
D31: =IF($C31="","",IFERROR(INDEX(Gantt!$B$4:$B$33,MATCH($C31,Gantt!$C$4:$C$33,0)),"")) | G31: =IF($A31="","",DATE(YEAR($A31),MONTH($A31),1)) | J31: =IF(Équipe!$A12="","",Équipe!$A12) | K31: =IF($J31="","",Équipe!$C12) | L31: =IF($J31="","",SUMIF($B$4:$B$303,$J31,$F$4:$F$303)) | M31: =IF($J31="","",K31-L31) | Q31: =IF(Gantt!$C31="","",Gantt!$C31) | R31: =IF($Q31="","",Gantt!$B31) | S31: =IF($Q31="","",Gantt!$G31) | T31: =IF($Q31="","",SUMIF($C$4:$C$303,$Q31,$F$4:$F$303)) | U31: =IF($Q31="","",S31-T31) | V31: =IF(OR($Q31="",N(S31)=0),"",T31/S31)
D32: =IF($C32="","",IFERROR(INDEX(Gantt!$B$4:$B$33,MATCH($C32,Gantt!$C$4:$C$33,0)),"")) | G32: =IF($A32="","",DATE(YEAR($A32),MONTH($A32),1)) | J32: =IF(Équipe!$A13="","",Équipe!$A13) | K32: =IF($J32="","",Équipe!$C13) | L32: =IF($J32="","",SUMIF($B$4:$B$303,$J32,$F$4:$F$303)) | M32: =IF($J32="","",K32-L32) | Q32: =IF(Gantt!$C32="","",Gantt!$C32) | R32: =IF($Q32="","",Gantt!$B32) | S32: =IF($Q32="","",Gantt!$G32) | T32: =IF($Q32="","",SUMIF($C$4:$C$303,$Q32,$F$4:$F$303)) | U32: =IF($Q32="","",S32-T32) | V32: =IF(OR($Q32="",N(S32)=0),"",T32/S32)
D33: =IF($C33="","",IFERROR(INDEX(Gantt!$B$4:$B$33,MATCH($C33,Gantt!$C$4:$C$33,0)),"")) | G33: =IF($A33="","",DATE(YEAR($A33),MONTH($A33),1)) | J33: =IF(Équipe!$A14="","",Équipe!$A14) | K33: =IF($J33="","",Équipe!$C14) | L33: =IF($J33="","",SUMIF($B$4:$B$303,$J33,$F$4:$F$303)) | M33: =IF($J33="","",K33-L33) | Q33: =IF(Gantt!$C33="","",Gantt!$C33) | R33: =IF($Q33="","",Gantt!$B33) | S33: =IF($Q33="","",Gantt!$G33) | T33: =IF($Q33="","",SUMIF($C$4:$C$303,$Q33,$F$4:$F$303)) | U33: =IF($Q33="","",S33-T33) | V33: =IF(OR($Q33="",N(S33)=0),"",T33/S33)
D34: =IF($C34="","",IFERROR(INDEX(Gantt!$B$4:$B$33,MATCH($C34,Gantt!$C$4:$C$33,0)),"")) | G34: =IF($A34="","",DATE(YEAR($A34),MONTH($A34),1)) | J34: =IF(Équipe!$A15="","",Équipe!$A15) | K34: =IF($J34="","",Équipe!$C15) | L34: =IF($J34="","",SUMIF($B$4:$B$303,$J34,$F$4:$F$303)) | M34: =IF($J34="","",K34-L34) | Q34: TOTAL | S34: =SUM(S4:S33) -> 1620 | T34: =SUM(T4:T33) -> 143 | U34: =SUM(U4:U33) -> 1477
D35: =IF($C35="","",IFERROR(INDEX(Gantt!$B$4:$B$33,MATCH($C35,Gantt!$C$4:$C$33,0)),"")) | G35: =IF($A35="","",DATE(YEAR($A35),MONTH($A35),1)) | J35: =IF(Équipe!$A16="","",Équipe!$A16) | K35: =IF($J35="","",Équipe!$C16) | L35: =IF($J35="","",SUMIF($B$4:$B$303,$J35,$F$4:$F$303)) | M35: =IF($J35="","",K35-L35)
D36: =IF($C36="","",IFERROR(INDEX(Gantt!$B$4:$B$33,MATCH($C36,Gantt!$C$4:$C$33,0)),"")) | G36: =IF($A36="","",DATE(YEAR($A36),MONTH($A36),1)) | J36: =IF(Équipe!$A17="","",Équipe!$A17) | K36: =IF($J36="","",Équipe!$C17) | L36: =IF($J36="","",SUMIF($B$4:$B$303,$J36,$F$4:$F$303)) | M36: =IF($J36="","",K36-L36)
D37: =IF($C37="","",IFERROR(INDEX(Gantt!$B$4:$B$33,MATCH($C37,Gantt!$C$4:$C$33,0)),"")) | G37: =IF($A37="","",DATE(YEAR($A37),MONTH($A37),1)) | J37: =IF(Équipe!$A18="","",Équipe!$A18) | K37: =IF($J37="","",Équipe!$C18) | L37: =IF($J37="","",SUMIF($B$4:$B$303,$J37,$F$4:$F$303)) | M37: =IF($J37="","",K37-L37)
D38: =IF($C38="","",IFERROR(INDEX(Gantt!$B$4:$B$33,MATCH($C38,Gantt!$C$4:$C$33,0)),"")) | G38: =IF($A38="","",DATE(YEAR($A38),MONTH($A38),1)) | J38: =IF(Équipe!$A19="","",Équipe!$A19) | K38: =IF($J38="","",Équipe!$C19) | L38: =IF($J38="","",SUMIF($B$4:$B$303,$J38,$F$4:$F$303)) | M38: =IF($J38="","",K38-L38)
D39: =IF($C39="","",IFERROR(INDEX(Gantt!$B$4:$B$33,MATCH($C39,Gantt!$C$4:$C$33,0)),"")) | G39: =IF($A39="","",DATE(YEAR($A39),MONTH($A39),1)) | J39: =IF(Équipe!$A20="","",Équipe!$A20) | K39: =IF($J39="","",Équipe!$C20) | L39: =IF($J39="","",SUMIF($B$4:$B$303,$J39,$F$4:$F$303)) | M39: =IF($J39="","",K39-L39)
D40: =IF($C40="","",IFERROR(INDEX(Gantt!$B$4:$B$33,MATCH($C40,Gantt!$C$4:$C$33,0)),"")) | G40: =IF($A40="","",DATE(YEAR($A40),MONTH($A40),1)) | J40: =IF(Équipe!$A21="","",Équipe!$A21) | K40: =IF($J40="","",Équipe!$C21) | L40: =IF($J40="","",SUMIF($B$4:$B$303,$J40,$F$4:$F$303)) | M40: =IF($J40="","",K40-L40)
D41: =IF($C41="","",IFERROR(INDEX(Gantt!$B$4:$B$33,MATCH($C41,Gantt!$C$4:$C$33,0)),"")) | G41: =IF($A41="","",DATE(YEAR($A41),MONTH($A41),1)) | J41: =IF(Équipe!$A22="","",Équipe!$A22) | K41: =IF($J41="","",Équipe!$C22) | L41: =IF($J41="","",SUMIF($B$4:$B$303,$J41,$F$4:$F$303)) | M41: =IF($J41="","",K41-L41)
D42: =IF($C42="","",IFERROR(INDEX(Gantt!$B$4:$B$33,MATCH($C42,Gantt!$C$4:$C$33,0)),"")) | G42: =IF($A42="","",DATE(YEAR($A42),MONTH($A42),1)) | J42: =IF(Équipe!$A23="","",Équipe!$A23) | K42: =IF($J42="","",Équipe!$C23) | L42: =IF($J42="","",SUMIF($B$4:$B$303,$J42,$F$4:$F$303)) | M42: =IF($J42="","",K42-L42)
D43: =IF($C43="","",IFERROR(INDEX(Gantt!$B$4:$B$33,MATCH($C43,Gantt!$C$4:$C$33,0)),"")) | G43: =IF($A43="","",DATE(YEAR($A43),MONTH($A43),1))
D44: =IF($C44="","",IFERROR(INDEX(Gantt!$B$4:$B$33,MATCH($C44,Gantt!$C$4:$C$33,0)),"")) | G44: =IF($A44="","",DATE(YEAR($A44),MONTH($A44),1)) | J44: Pointé par mois
D45: =IF($C45="","",IFERROR(INDEX(Gantt!$B$4:$B$33,MATCH($C45,Gantt!$C$4:$C$33,0)),"")) | G45: =IF($A45="","",DATE(YEAR($A45),MONTH($A45),1)) | J45: Mois | K45: Prévu (h) | L45: Pointé (h) | M45: Écart cumulé
D46: =IF($C46="","",IFERROR(INDEX(Gantt!$B$4:$B$33,MATCH($C46,Gantt!$C$4:$C$33,0)),"")) | G46: =IF($A46="","",DATE(YEAR($A46),MONTH($A46),1)) | J46: 46266 | K46: =Gantt!J$34 -> 80 | L46: =SUMIF($G$4:$G$303,$J46,$F$4:$F$303) -> 83 | M46: =SUM(K$46:K46)-SUM(L$46:L46) -> -3
D47: =IF($C47="","",IFERROR(INDEX(Gantt!$B$4:$B$33,MATCH($C47,Gantt!$C$4:$C$33,0)),"")) | G47: =IF($A47="","",DATE(YEAR($A47),MONTH($A47),1)) | J47: 46296 | K47: =Gantt!K$34 -> 320 | L47: =SUMIF($G$4:$G$303,$J47,$F$4:$F$303) -> 60 | M47: =SUM(K$46:K47)-SUM(L$46:L47) -> 257
D48: =IF($C48="","",IFERROR(INDEX(Gantt!$B$4:$B$33,MATCH($C48,Gantt!$C$4:$C$33,0)),"")) | G48: =IF($A48="","",DATE(YEAR($A48),MONTH($A48),1)) | J48: 46327 | K48: =Gantt!L$34 -> 320 | L48: =SUMIF($G$4:$G$303,$J48,$F$4:$F$303) -> 0 | M48: =SUM(K$46:K48)-SUM(L$46:L48) -> 577
D49: =IF($C49="","",IFERROR(INDEX(Gantt!$B$4:$B$33,MATCH($C49,Gantt!$C$4:$C$33,0)),"")) | G49: =IF($A49="","",DATE(YEAR($A49),MONTH($A49),1)) | J49: 46357 | K49: =Gantt!M$34 -> 320 | L49: =SUMIF($G$4:$G$303,$J49,$F$4:$F$303) -> 0 | M49: =SUM(K$46:K49)-SUM(L$46:L49) -> 897
D50: =IF($C50="","",IFERROR(INDEX(Gantt!$B$4:$B$33,MATCH($C50,Gantt!$C$4:$C$33,0)),"")) | G50: =IF($A50="","",DATE(YEAR($A50),MONTH($A50),1)) | J50: 46388 | K50: =Gantt!N$34 -> 320 | L50: =SUMIF($G$4:$G$303,$J50,$F$4:$F$303) -> 0 | M50: =SUM(K$46:K50)-SUM(L$46:L50) -> 1217
D51: =IF($C51="","",IFERROR(INDEX(Gantt!$B$4:$B$33,MATCH($C51,Gantt!$C$4:$C$33,0)),"")) | G51: =IF($A51="","",DATE(YEAR($A51),MONTH($A51),1)) | J51: 46419 | K51: =Gantt!O$34 -> 260 | L51: =SUMIF($G$4:$G$303,$J51,$F$4:$F$303) -> 0 | M51: =SUM(K$46:K51)-SUM(L$46:L51) -> 1477
D52: =IF($C52="","",IFERROR(INDEX(Gantt!$B$4:$B$33,MATCH($C52,Gantt!$C$4:$C$33,0)),"")) | G52: =IF($A52="","",DATE(YEAR($A52),MONTH($A52),1)) | J52: 46447 | K52: =Gantt!P$34 -> 0 | L52: =SUMIF($G$4:$G$303,$J52,$F$4:$F$303) -> 0 | M52: =SUM(K$46:K52)-SUM(L$46:L52) -> 1477
D53: =IF($C53="","",IFERROR(INDEX(Gantt!$B$4:$B$33,MATCH($C53,Gantt!$C$4:$C$33,0)),"")) | G53: =IF($A53="","",DATE(YEAR($A53),MONTH($A53),1)) | J53: 46478 | K53: =Gantt!Q$34 -> 0 | L53: =SUMIF($G$4:$G$303,$J53,$F$4:$F$303) -> 0 | M53: =SUM(K$46:K53)-SUM(L$46:L53) -> 1477
D54: =IF($C54="","",IFERROR(INDEX(Gantt!$B$4:$B$33,MATCH($C54,Gantt!$C$4:$C$33,0)),"")) | G54: =IF($A54="","",DATE(YEAR($A54),MONTH($A54),1)) | J54: 46508 | K54: =Gantt!R$34 -> 0 | L54: =SUMIF($G$4:$G$303,$J54,$F$4:$F$303) -> 0 | M54: =SUM(K$46:K54)-SUM(L$46:L54) -> 1477
D55: =IF($C55="","",IFERROR(INDEX(Gantt!$B$4:$B$33,MATCH($C55,Gantt!$C$4:$C$33,0)),"")) | G55: =IF($A55="","",DATE(YEAR($A55),MONTH($A55),1)) | J55: 46539 | K55: =Gantt!S$34 -> 0 | L55: =SUMIF($G$4:$G$303,$J55,$F$4:$F$303) -> 0 | M55: =SUM(K$46:K55)-SUM(L$46:L55) -> 1477
D56: =IF($C56="","",IFERROR(INDEX(Gantt!$B$4:$B$33,MATCH($C56,Gantt!$C$4:$C$33,0)),"")) | G56: =IF($A56="","",DATE(YEAR($A56),MONTH($A56),1)) | J56: 46569 | K56: =Gantt!T$34 -> 0 | L56: =SUMIF($G$4:$G$303,$J56,$F$4:$F$303) -> 0 | M56: =SUM(K$46:K56)-SUM(L$46:L56) -> 1477
D57: =IF($C57="","",IFERROR(INDEX(Gantt!$B$4:$B$33,MATCH($C57,Gantt!$C$4:$C$33,0)),"")) | G57: =IF($A57="","",DATE(YEAR($A57),MONTH($A57),1)) | J57: 46600 | K57: =Gantt!U$34 -> 0 | L57: =SUMIF($G$4:$G$303,$J57,$F$4:$F$303) -> 0 | M57: =SUM(K$46:K57)-SUM(L$46:L57) -> 1477
D58: =IF($C58="","",IFERROR(INDEX(Gantt!$B$4:$B$33,MATCH($C58,Gantt!$C$4:$C$33,0)),"")) | G58: =IF($A58="","",DATE(YEAR($A58),MONTH($A58),1)) | J58: 46631 | K58: =Gantt!V$34 -> 0 | L58: =SUMIF($G$4:$G$303,$J58,$F$4:$F$303) -> 0 | M58: =SUM(K$46:K58)-SUM(L$46:L58) -> 1477
D59: =IF($C59="","",IFERROR(INDEX(Gantt!$B$4:$B$33,MATCH($C59,Gantt!$C$4:$C$33,0)),"")) | G59: =IF($A59="","",DATE(YEAR($A59),MONTH($A59),1)) | J59: 46661 | K59: =Gantt!W$34 -> 0 | L59: =SUMIF($G$4:$G$303,$J59,$F$4:$F$303) -> 0 | M59: =SUM(K$46:K59)-SUM(L$46:L59) -> 1477
D60: =IF($C60="","",IFERROR(INDEX(Gantt!$B$4:$B$33,MATCH($C60,Gantt!$C$4:$C$33,0)),"")) | G60: =IF($A60="","",DATE(YEAR($A60),MONTH($A60),1)) | J60: 46692 | K60: =Gantt!X$34 -> 0 | L60: =SUMIF($G$4:$G$303,$J60,$F$4:$F$303) -> 0 | M60: =SUM(K$46:K60)-SUM(L$46:L60) -> 1477
D61: =IF($C61="","",IFERROR(INDEX(Gantt!$B$4:$B$33,MATCH($C61,Gantt!$C$4:$C$33,0)),"")) | G61: =IF($A61="","",DATE(YEAR($A61),MONTH($A61),1)) | J61: 46722 | K61: =Gantt!Y$34 -> 0 | L61: =SUMIF($G$4:$G$303,$J61,$F$4:$F$303) -> 0 | M61: =SUM(K$46:K61)-SUM(L$46:L61) -> 1477
D62: =IF($C62="","",IFERROR(INDEX(Gantt!$B$4:$B$33,MATCH($C62,Gantt!$C$4:$C$33,0)),"")) | G62: =IF($A62="","",DATE(YEAR($A62),MONTH($A62),1)) | J62: 46753 | K62: =Gantt!Z$34 -> 0 | L62: =SUMIF($G$4:$G$303,$J62,$F$4:$F$303) -> 0 | M62: =SUM(K$46:K62)-SUM(L$46:L62) -> 1477
D63: =IF($C63="","",IFERROR(INDEX(Gantt!$B$4:$B$33,MATCH($C63,Gantt!$C$4:$C$33,0)),"")) | G63: =IF($A63="","",DATE(YEAR($A63),MONTH($A63),1)) | J63: 46784 | K63: =Gantt!AA$34 -> 0 | L63: =SUMIF($G$4:$G$303,$J63,$F$4:$F$303) -> 0 | M63: =SUM(K$46:K63)-SUM(L$46:L63) -> 1477
D64: =IF($C64="","",IFERROR(INDEX(Gantt!$B$4:$B$33,MATCH($C64,Gantt!$C$4:$C$33,0)),"")) | G64: =IF($A64="","",DATE(YEAR($A64),MONTH($A64),1))
D65: =IF($C65="","",IFERROR(INDEX(Gantt!$B$4:$B$33,MATCH($C65,Gantt!$C$4:$C$33,0)),"")) | G65: =IF($A65="","",DATE(YEAR($A65),MONTH($A65),1))
D66: =IF($C66="","",IFERROR(INDEX(Gantt!$B$4:$B$33,MATCH($C66,Gantt!$C$4:$C$33,0)),"")) | G66: =IF($A66="","",DATE(YEAR($A66),MONTH($A66),1))
D67: =IF($C67="","",IFERROR(INDEX(Gantt!$B$4:$B$33,MATCH($C67,Gantt!$C$4:$C$33,0)),"")) | G67: =IF($A67="","",DATE(YEAR($A67),MONTH($A67),1))
D68: =IF($C68="","",IFERROR(INDEX(Gantt!$B$4:$B$33,MATCH($C68,Gantt!$C$4:$C$33,0)),"")) | G68: =IF($A68="","",DATE(YEAR($A68),MONTH($A68),1))
D69: =IF($C69="","",IFERROR(INDEX(Gantt!$B$4:$B$33,MATCH($C69,Gantt!$C$4:$C$33,0)),"")) | G69: =IF($A69="","",DATE(YEAR($A69),MONTH($A69),1))
D70: =IF($C70="","",IFERROR(INDEX(Gantt!$B$4:$B$33,MATCH($C70,Gantt!$C$4:$C$33,0)),"")) | G70: =IF($A70="","",DATE(YEAR($A70),MONTH($A70),1))
D71: =IF($C71="","",IFERROR(INDEX(Gantt!$B$4:$B$33,MATCH($C71,Gantt!$C$4:$C$33,0)),"")) | G71: =IF($A71="","",DATE(YEAR($A71),MONTH($A71),1))
D72: =IF($C72="","",IFERROR(INDEX(Gantt!$B$4:$B$33,MATCH($C72,Gantt!$C$4:$C$33,0)),"")) | G72: =IF($A72="","",DATE(YEAR($A72),MONTH($A72),1))
D73: =IF($C73="","",IFERROR(INDEX(Gantt!$B$4:$B$33,MATCH($C73,Gantt!$C$4:$C$33,0)),"")) | G73: =IF($A73="","",DATE(YEAR($A73),MONTH($A73),1))
D74: =IF($C74="","",IFERROR(INDEX(Gantt!$B$4:$B$33,MATCH($C74,Gantt!$C$4:$C$33,0)),"")) | G74: =IF($A74="","",DATE(YEAR($A74),MONTH($A74),1))
D75: =IF($C75="","",IFERROR(INDEX(Gantt!$B$4:$B$33,MATCH($C75,Gantt!$C$4:$C$33,0)),"")) | G75: =IF($A75="","",DATE(YEAR($A75),MONTH($A75),1))
... D303: =IF($C303="","",IFERROR(INDEX(Gantt!$B$4:$B$33,MATCH($C303,Gantt!$C$4:$C$33,0)),"")) | G303: =IF($A303="","",DATE(YEAR($A303),MONTH($A303),1))
A304: TOTAL POINTÉ | F304: =SUM(F4:F303) -> 143

Sheet Suivi
A1: Suivi d'avancement et de budget
A2: Gauche (gris) = référentiel figé, repris du planning : ne rien saisir ici. Droite (couleur) = suivi vivant, recalculé à chaque pointage. Les colonnes du référentiel restent visibles quand on fait défiler vers la droite.
B3: Charge prévue (h) | C3: Pointé (h) | D3: Reste à faire (h) | E3: Avancement réel | F3: Budget total (h) | G3: Reste budget (h) | H3: Tâches terminées
B4: =Gantt!$G$34 -> 1620 | C4: =Pointage!$F$304 -> 143 | D4: =MAX(0,B4-C4) -> 1477 | E4: =IFERROR(C4/B4,0) -> 0.088271605 | F4: =Financement!$D$19 -> 2200 | G4: =F4-C4 -> 2057 | H4: =COUNTIF(Gantt!$E$4:$E$33,"Réalisé")&" / "&COUNTA(Gantt!$C$4:$C$33) -> 0 / 5
A6: RÉFÉRENTIEL FIGÉ (planning) | G6: SUIVI VIVANT (pointages)
A7: Tâche | B7: Projet | C7: Lot | D7: Responsable | E7: Charge prévue | F7: Période prévue | G7: Pointé | H7: Reste | I7: % réel | J7: Statut saisi | K7: Statut réel | L7: Dernier pointage | M7: Alerte | N7: Financement
A8: =IF(Gantt!$C4="","",Gantt!$C4) -> Conception d'actifs 3D | B8: =IF($A8="","",Gantt!$B4) -> Projet A | C8: =IF($A8="","",Gantt!$A4) -> Lot 1 | D8: =IF($A8="","",Gantt!$D4) -> Personne A | E8: =IF($A8="","",Gantt!$G4) -> 120 | F8: =IF($A8="","",IF(Gantt!$H4="","",TEXT(Gantt!$H4,"mmm yy")&" → "&TEXT(Gantt!$I4,"mmm yy"))) -> Sep 26 → Oct 26 | G8: =IF($A8="","",SUMIF(Pointage!$C$4:$C$303,$A8,Pointage!$F$4:$F$303)) -> 83 | H8: =IF($A8="","",$E8-$G8) -> 37 | I8: =IF(OR($A8="",N($E8)=0),"",$G8/$E8) -> 0.69166667 | J8: =IF($A8="","",Gantt!$E4) -> En cours | K8: =IF($A8="","",IF($G8=0,"Non commencé",IF($G8>=$E8,"Terminé (charge atteinte)","En cours"))) -> En cours | L8: =IF($A8="","",IFERROR(IF(_xlfn.MAXIFS(Pointage!$A$4:$A$303,Pointage!$C$4:$C$303,$A8)=0,"—",_xlfn.MAXIFS(Pointage!$A$4:$A$303,Pointage!$C$4:$C$303,$A8)),"—")) -> 46294 | M8: =IF($A8="","",IF($G8>$E8,"Dépassement de charge",IF(AND($J8="Réalisé",$G8<$E8),"Réalisé mais sous-pointé",IF(AND($J8="Non commencé",$G8>0),"Pointé mais non démarré",IF(AND(N($E8)>0,$I8>0.8,$J8<>"Réalisé"),"Bientôt consommé",""))))) | N8: =IF($A8="","",Gantt!$F4) -> Interne (120h)
A9: =IF(Gantt!$C5="","",Gantt!$C5) -> Modélisation système | B9: =IF($A9="","",Gantt!$B5) -> Projet A | C9: =IF($A9="","",Gantt!$A5) -> Lot 5 | D9: =IF($A9="","",Gantt!$D5) -> Personne A | E9: =IF($A9="","",Gantt!$G5) -> 200 | F9: =IF($A9="","",IF(Gantt!$H5="","",TEXT(Gantt!$H5,"mmm yy")&" → "&TEXT(Gantt!$I5,"mmm yy"))) -> Oct 26 → Oct 26 | G9: =IF($A9="","",SUMIF(Pointage!$C$4:$C$303,$A9,Pointage!$F$4:$F$303)) -> 0 | H9: =IF($A9="","",$E9-$G9) -> 200 | I9: =IF(OR($A9="",N($E9)=0),"",$G9/$E9) -> 0 | J9: =IF($A9="","",Gantt!$E5) -> Non commencé | K9: =IF($A9="","",IF($G9=0,"Non commencé",IF($G9>=$E9,"Terminé (charge atteinte)","En cours"))) -> Non commencé | L9: =IF($A9="","",IFERROR(IF(_xlfn.MAXIFS(Pointage!$A$4:$A$303,Pointage!$C$4:$C$303,$A9)=0,"—",_xlfn.MAXIFS(Pointage!$A$4:$A$303,Pointage!$C$4:$C$303,$A9)),"—")) -> — | M9: =IF($A9="","",IF($G9>$E9,"Dépassement de charge",IF(AND($J9="Réalisé",$G9<$E9),"Réalisé mais sous-pointé",IF(AND($J9="Non commencé",$G9>0),"Pointé mais non démarré",IF(AND(N($E9)>0,$I9>0.8,$J9<>"Réalisé"),"Bientôt consommé",""))))) | N9: =IF($A9="","",Gantt!$F5) -> Interne (200h)
A10: =IF(Gantt!$C6="","",Gantt!$C6) -> Intégration technique | B10: =IF($A10="","",Gantt!$B6) -> Projet B | C10: =IF($A10="","",Gantt!$A6) -> Lot 2 | D10: =IF($A10="","",Gantt!$D6) -> Personne B | E10: =IF($A10="","",Gantt!$G6) -> 480 | F10: =IF($A10="","",IF(Gantt!$H6="","",TEXT(Gantt!$H6,"mmm yy")&" → "&TEXT(Gantt!$I6,"mmm yy"))) -> Oct 26 → Dec 26 | G10: =IF($A10="","",SUMIF(Pointage!$C$4:$C$303,$A10,Pointage!$F$4:$F$303)) -> 60 | H10: =IF($A10="","",$E10-$G10) -> 420 | I10: =IF(OR($A10="",N($E10)=0),"",$G10/$E10) -> 0.125 | J10: =IF($A10="","",Gantt!$E6) -> Non commencé | K10: =IF($A10="","",IF($G10=0,"Non commencé",IF($G10>=$E10,"Terminé (charge atteinte)","En cours"))) -> En cours | L10: =IF($A10="","",IFERROR(IF(_xlfn.MAXIFS(Pointage!$A$4:$A$303,Pointage!$C$4:$C$303,$A10)=0,"—",_xlfn.MAXIFS(Pointage!$A$4:$A$303,Pointage!$C$4:$C$303,$A10)),"—")) -> 46308 | M10: =IF($A10="","",IF($G10>$E10,"Dépassement de charge",IF(AND($J10="Réalisé",$G10<$E10),"Réalisé mais sous-pointé",IF(AND($J10="Non commencé",$G10>0),"Pointé mais non démarré",IF(AND(N($E10)>0,$I10>0.8,$J10<>"Réalisé"),"Bientôt consommé",""))))) -> Pointé mais non démarré | N10: =IF($A10="","",Gantt!$F6) -> Client A (300h) + Subvention (180h)
A11: =IF(Gantt!$C7="","",Gantt!$C7) -> Configuration scénarios | B11: =IF($A11="","",Gantt!$B7) -> Projet B | C11: =IF($A11="","",Gantt!$A7) -> Lot 3 | D11: =IF($A11="","",Gantt!$D7) -> Personne B | E11: =IF($A11="","",Gantt!$G7) -> 500 | F11: =IF($A11="","",IF(Gantt!$H7="","",TEXT(Gantt!$H7,"mmm yy")&" → "&TEXT(Gantt!$I7,"mmm yy"))) -> Dec 26 → Jan 27 | G11: =IF($A11="","",SUMIF(Pointage!$C$4:$C$303,$A11,Pointage!$F$4:$F$303)) -> 0 | H11: =IF($A11="","",$E11-$G11) -> 500 | I11: =IF(OR($A11="",N($E11)=0),"",$G11/$E11) -> 0 | J11: =IF($A11="","",Gantt!$E7) -> Non commencé | K11: =IF($A11="","",IF($G11=0,"Non commencé",IF($G11>=$E11,"Terminé (charge atteinte)","En cours"))) -> Non commencé | L11: =IF($A11="","",IFERROR(IF(_xlfn.MAXIFS(Pointage!$A$4:$A$303,Pointage!$C$4:$C$303,$A11)=0,"—",_xlfn.MAXIFS(Pointage!$A$4:$A$303,Pointage!$C$4:$C$303,$A11)),"—")) -> — | M11: =IF($A11="","",IF($G11>$E11,"Dépassement de charge",IF(AND($J11="Réalisé",$G11<$E11),"Réalisé mais sous-pointé",IF(AND($J11="Non commencé",$G11>0),"Pointé mais non démarré",IF(AND(N($E11)>0,$I11>0.8,$J11<>"Réalisé"),"Bientôt consommé",""))))) | N11: =IF($A11="","",Gantt!$F7) -> Client A (500h)
A12: =IF(Gantt!$C8="","",Gantt!$C8) -> Préparation livraison | B12: =IF($A12="","",Gantt!$B8) -> Projet A | C12: =IF($A12="","",Gantt!$A8) -> Lot 4 | D12: =IF($A12="","",Gantt!$D8) -> Personne A | E12: =IF($A12="","",Gantt!$G8) -> 320 | F12: =IF($A12="","",IF(Gantt!$H8="","",TEXT(Gantt!$H8,"mmm yy")&" → "&TEXT(Gantt!$I8,"mmm yy"))) -> Jan 27 → Feb 27 | G12: =IF($A12="","",SUMIF(Pointage!$C$4:$C$303,$A12,Pointage!$F$4:$F$303)) -> 0 | H12: =IF($A12="","",$E12-$G12) -> 320 | I12: =IF(OR($A12="",N($E12)=0),"",$G12/$E12) -> 0 | J12: =IF($A12="","",Gantt!$E8) -> Non commencé | K12: =IF($A12="","",IF($G12=0,"Non commencé",IF($G12>=$E12,"Terminé (charge atteinte)","En cours"))) -> Non commencé | L12: =IF($A12="","",IFERROR(IF(_xlfn.MAXIFS(Pointage!$A$4:$A$303,Pointage!$C$4:$C$303,$A12)=0,"—",_xlfn.MAXIFS(Pointage!$A$4:$A$303,Pointage!$C$4:$C$303,$A12)),"—")) -> — | M12: =IF($A12="","",IF($G12>$E12,"Dépassement de charge",IF(AND($J12="Réalisé",$G12<$E12),"Réalisé mais sous-pointé",IF(AND($J12="Non commencé",$G12>0),"Pointé mais non démarré",IF(AND(N($E12)>0,$I12>0.8,$J12<>"Réalisé"),"Bientôt consommé",""))))) | N12: =IF($A12="","",Gantt!$F8) -> Client A (220h) + Client B (100h)
A13: =IF(Gantt!$C9="","",Gantt!$C9) | B13: =IF($A13="","",Gantt!$B9) | C13: =IF($A13="","",Gantt!$A9) | D13: =IF($A13="","",Gantt!$D9) | E13: =IF($A13="","",Gantt!$G9) | F13: =IF($A13="","",IF(Gantt!$H9="","",TEXT(Gantt!$H9,"mmm yy")&" → "&TEXT(Gantt!$I9,"mmm yy"))) | G13: =IF($A13="","",SUMIF(Pointage!$C$4:$C$303,$A13,Pointage!$F$4:$F$303)) | H13: =IF($A13="","",$E13-$G13) | I13: =IF(OR($A13="",N($E13)=0),"",$G13/$E13) | J13: =IF($A13="","",Gantt!$E9) | K13: =IF($A13="","",IF($G13=0,"Non commencé",IF($G13>=$E13,"Terminé (charge atteinte)","En cours"))) | L13: =IF($A13="","",IFERROR(IF(_xlfn.MAXIFS(Pointage!$A$4:$A$303,Pointage!$C$4:$C$303,$A13)=0,"—",_xlfn.MAXIFS(Pointage!$A$4:$A$303,Pointage!$C$4:$C$303,$A13)),"—")) | M13: =IF($A13="","",IF($G13>$E13,"Dépassement de charge",IF(AND($J13="Réalisé",$G13<$E13),"Réalisé mais sous-pointé",IF(AND($J13="Non commencé",$G13>0),"Pointé mais non démarré",IF(AND(N($E13)>0,$I13>0.8,$J13<>"Réalisé"),"Bientôt consommé",""))))) | N13: =IF($A13="","",Gantt!$F9)
A14: =IF(Gantt!$C10="","",Gantt!$C10) | B14: =IF($A14="","",Gantt!$B10) | C14: =IF($A14="","",Gantt!$A10) | D14: =IF($A14="","",Gantt!$D10) | E14: =IF($A14="","",Gantt!$G10) | F14: =IF($A14="","",IF(Gantt!$H10="","",TEXT(Gantt!$H10,"mmm yy")&" → "&TEXT(Gantt!$I10,"mmm yy"))) | G14: =IF($A14="","",SUMIF(Pointage!$C$4:$C$303,$A14,Pointage!$F$4:$F$303)) | H14: =IF($A14="","",$E14-$G14) | I14: =IF(OR($A14="",N($E14)=0),"",$G14/$E14) | J14: =IF($A14="","",Gantt!$E10) | K14: =IF($A14="","",IF($G14=0,"Non commencé",IF($G14>=$E14,"Terminé (charge atteinte)","En cours"))) | L14: =IF($A14="","",IFERROR(IF(_xlfn.MAXIFS(Pointage!$A$4:$A$303,Pointage!$C$4:$C$303,$A14)=0,"—",_xlfn.MAXIFS(Pointage!$A$4:$A$303,Pointage!$C$4:$C$303,$A14)),"—")) | M14: =IF($A14="","",IF($G14>$E14,"Dépassement de charge",IF(AND($J14="Réalisé",$G14<$E14),"Réalisé mais sous-pointé",IF(AND($J14="Non commencé",$G14>0),"Pointé mais non démarré",IF(AND(N($E14)>0,$I14>0.8,$J14<>"Réalisé"),"Bientôt consommé",""))))) | N14: =IF($A14="","",Gantt!$F10)
A15: =IF(Gantt!$C11="","",Gantt!$C11) | B15: =IF($A15="","",Gantt!$B11) | C15: =IF($A15="","",Gantt!$A11) | D15: =IF($A15="","",Gantt!$D11) | E15: =IF($A15="","",Gantt!$G11) | F15: =IF($A15="","",IF(Gantt!$H11="","",TEXT(Gantt!$H11,"mmm yy")&" → "&TEXT(Gantt!$I11,"mmm yy"))) | G15: =IF($A15="","",SUMIF(Pointage!$C$4:$C$303,$A15,Pointage!$F$4:$F$303)) | H15: =IF($A15="","",$E15-$G15) | I15: =IF(OR($A15="",N($E15)=0),"",$G15/$E15) | J15: =IF($A15="","",Gantt!$E11) | K15: =IF($A15="","",IF($G15=0,"Non commencé",IF($G15>=$E15,"Terminé (charge atteinte)","En cours"))) | L15: =IF($A15="","",IFERROR(IF(_xlfn.MAXIFS(Pointage!$A$4:$A$303,Pointage!$C$4:$C$303,$A15)=0,"—",_xlfn.MAXIFS(Pointage!$A$4:$A$303,Pointage!$C$4:$C$303,$A15)),"—")) | M15: =IF($A15="","",IF($G15>$E15,"Dépassement de charge",IF(AND($J15="Réalisé",$G15<$E15),"Réalisé mais sous-pointé",IF(AND($J15="Non commencé",$G15>0),"Pointé mais non démarré",IF(AND(N($E15)>0,$I15>0.8,$J15<>"Réalisé"),"Bientôt consommé",""))))) | N15: =IF($A15="","",Gantt!$F11)
A16: =IF(Gantt!$C12="","",Gantt!$C12) | B16: =IF($A16="","",Gantt!$B12) | C16: =IF($A16="","",Gantt!$A12) | D16: =IF($A16="","",Gantt!$D12) | E16: =IF($A16="","",Gantt!$G12) | F16: =IF($A16="","",IF(Gantt!$H12="","",TEXT(Gantt!$H12,"mmm yy")&" → "&TEXT(Gantt!$I12,"mmm yy"))) | G16: =IF($A16="","",SUMIF(Pointage!$C$4:$C$303,$A16,Pointage!$F$4:$F$303)) | H16: =IF($A16="","",$E16-$G16) | I16: =IF(OR($A16="",N($E16)=0),"",$G16/$E16) | J16: =IF($A16="","",Gantt!$E12) | K16: =IF($A16="","",IF($G16=0,"Non commencé",IF($G16>=$E16,"Terminé (charge atteinte)","En cours"))) | L16: =IF($A16="","",IFERROR(IF(_xlfn.MAXIFS(Pointage!$A$4:$A$303,Pointage!$C$4:$C$303,$A16)=0,"—",_xlfn.MAXIFS(Pointage!$A$4:$A$303,Pointage!$C$4:$C$303,$A16)),"—")) | M16: =IF($A16="","",IF($G16>$E16,"Dépassement de charge",IF(AND($J16="Réalisé",$G16<$E16),"Réalisé mais sous-pointé",IF(AND($J16="Non commencé",$G16>0),"Pointé mais non démarré",IF(AND(N($E16)>0,$I16>0.8,$J16<>"Réalisé"),"Bientôt consommé",""))))) | N16: =IF($A16="","",Gantt!$F12)
A17: =IF(Gantt!$C13="","",Gantt!$C13) | B17: =IF($A17="","",Gantt!$B13) | C17: =IF($A17="","",Gantt!$A13) | D17: =IF($A17="","",Gantt!$D13) | E17: =IF($A17="","",Gantt!$G13) | F17: =IF($A17="","",IF(Gantt!$H13="","",TEXT(Gantt!$H13,"mmm yy")&" → "&TEXT(Gantt!$I13,"mmm yy"))) | G17: =IF($A17="","",SUMIF(Pointage!$C$4:$C$303,$A17,Pointage!$F$4:$F$303)) | H17: =IF($A17="","",$E17-$G17) | I17: =IF(OR($A17="",N($E17)=0),"",$G17/$E17) | J17: =IF($A17="","",Gantt!$E13) | K17: =IF($A17="","",IF($G17=0,"Non commencé",IF($G17>=$E17,"Terminé (charge atteinte)","En cours"))) | L17: =IF($A17="","",IFERROR(IF(_xlfn.MAXIFS(Pointage!$A$4:$A$303,Pointage!$C$4:$C$303,$A17)=0,"—",_xlfn.MAXIFS(Pointage!$A$4:$A$303,Pointage!$C$4:$C$303,$A17)),"—")) | M17: =IF($A17="","",IF($G17>$E17,"Dépassement de charge",IF(AND($J17="Réalisé",$G17<$E17),"Réalisé mais sous-pointé",IF(AND($J17="Non commencé",$G17>0),"Pointé mais non démarré",IF(AND(N($E17)>0,$I17>0.8,$J17<>"Réalisé"),"Bientôt consommé",""))))) | N17: =IF($A17="","",Gantt!$F13)
A18: =IF(Gantt!$C14="","",Gantt!$C14) | B18: =IF($A18="","",Gantt!$B14) | C18: =IF($A18="","",Gantt!$A14) | D18: =IF($A18="","",Gantt!$D14) | E18: =IF($A18="","",Gantt!$G14) | F18: =IF($A18="","",IF(Gantt!$H14="","",TEXT(Gantt!$H14,"mmm yy")&" → "&TEXT(Gantt!$I14,"mmm yy"))) | G18: =IF($A18="","",SUMIF(Pointage!$C$4:$C$303,$A18,Pointage!$F$4:$F$303)) | H18: =IF($A18="","",$E18-$G18) | I18: =IF(OR($A18="",N($E18)=0),"",$G18/$E18) | J18: =IF($A18="","",Gantt!$E14) | K18: =IF($A18="","",IF($G18=0,"Non commencé",IF($G18>=$E18,"Terminé (charge atteinte)","En cours"))) | L18: =IF($A18="","",IFERROR(IF(_xlfn.MAXIFS(Pointage!$A$4:$A$303,Pointage!$C$4:$C$303,$A18)=0,"—",_xlfn.MAXIFS(Pointage!$A$4:$A$303,Pointage!$C$4:$C$303,$A18)),"—")) | M18: =IF($A18="","",IF($G18>$E18,"Dépassement de charge",IF(AND($J18="Réalisé",$G18<$E18),"Réalisé mais sous-pointé",IF(AND($J18="Non commencé",$G18>0),"Pointé mais non démarré",IF(AND(N($E18)>0,$I18>0.8,$J18<>"Réalisé"),"Bientôt consommé",""))))) | N18: =IF($A18="","",Gantt!$F14)
A19: =IF(Gantt!$C15="","",Gantt!$C15) | B19: =IF($A19="","",Gantt!$B15) | C19: =IF($A19="","",Gantt!$A15) | D19: =IF($A19="","",Gantt!$D15) | E19: =IF($A19="","",Gantt!$G15) | F19: =IF($A19="","",IF(Gantt!$H15="","",TEXT(Gantt!$H15,"mmm yy")&" → "&TEXT(Gantt!$I15,"mmm yy"))) | G19: =IF($A19="","",SUMIF(Pointage!$C$4:$C$303,$A19,Pointage!$F$4:$F$303)) | H19: =IF($A19="","",$E19-$G19) | I19: =IF(OR($A19="",N($E19)=0),"",$G19/$E19) | J19: =IF($A19="","",Gantt!$E15) | K19: =IF($A19="","",IF($G19=0,"Non commencé",IF($G19>=$E19,"Terminé (charge atteinte)","En cours"))) | L19: =IF($A19="","",IFERROR(IF(_xlfn.MAXIFS(Pointage!$A$4:$A$303,Pointage!$C$4:$C$303,$A19)=0,"—",_xlfn.MAXIFS(Pointage!$A$4:$A$303,Pointage!$C$4:$C$303,$A19)),"—")) | M19: =IF($A19="","",IF($G19>$E19,"Dépassement de charge",IF(AND($J19="Réalisé",$G19<$E19),"Réalisé mais sous-pointé",IF(AND($J19="Non commencé",$G19>0),"Pointé mais non démarré",IF(AND(N($E19)>0,$I19>0.8,$J19<>"Réalisé"),"Bientôt consommé",""))))) | N19: =IF($A19="","",Gantt!$F15)
... A37: =IF(Gantt!$C33="","",Gantt!$C33) | B37: =IF($A37="","",Gantt!$B33) | C37: =IF($A37="","",Gantt!$A33) | D37: =IF($A37="","",Gantt!$D33) | E37: =IF($A37="","",Gantt!$G33) | F37: =IF($A37="","",IF(Gantt!$H33="","",TEXT(Gantt!$H33,"mmm yy")&" → "&TEXT(Gantt!$I33,"mmm yy"))) | G37: =IF($A37="","",SUMIF(Pointage!$C$4:$C$303,$A37,Pointage!$F$4:$F$303)) | H37: =IF($A37="","",$E37-$G37) | I37: =IF(OR($A37="",N($E37)=0),"",$G37/$E37) | J37: =IF($A37="","",Gantt!$E33) | K37: =IF($A37="","",IF($G37=0,"Non commencé",IF($G37>=$E37,"Terminé (charge atteinte)","En cours"))) | L37: =IF($A37="","",IFERROR(IF(_xlfn.MAXIFS(Pointage!$A$4:$A$303,Pointage!$C$4:$C$303,$A37)=0,"—",_xlfn.MAXIFS(Pointage!$A$4:$A$303,Pointage!$C$4:$C$303,$A37)),"—")) | M37: =IF($A37="","",IF($G37>$E37,"Dépassement de charge",IF(AND($J37="Réalisé",$G37<$E37),"Réalisé mais sous-pointé",IF(AND($J37="Non commencé",$G37>0),"Pointé mais non démarré",IF(AND(N($E37)>0,$I37>0.8,$J37<>"Réalisé"),"Bientôt consommé",""))))) | N37: =IF($A37="","",Gantt!$F33)
A38: TOTAL | E38: =SUM(E8:E37) -> 1620 | G38: =SUM(G8:G37) -> 143 | H38: =SUM(H8:H37) -> 1477 | I38: =IFERROR(G38/E38,0) -> 0.088271605
A41: RÉFÉRENTIEL FIGÉ (budgets) | E41: SUIVI VIVANT (consommation)
A42: Source | B42: Certitude | C42: Budget | D42: Prévu | E42: Pointé | F42: Reste budget | G42: % consommé | H42: Reste à pointer | I42: Projection | J42: Alerte
A43: =IF(Financement!$A4="","",Financement!$A4) -> Interne | B43: =IF($A43="","",Financement!$B4) -> Confirmé | C43: =IF($A43="","",Financement!$D4) -> 600 | D43: =IF($A43="","",Financement!$E4) -> 320 | E43: =IF($A43="","",SUMIF(Pointage!$E$4:$E$303,$A43,Pointage!$F$4:$F$303)) -> 83 | F43: =IF($A43="","",$C43-$E43) -> 517 | G43: =IF(OR($A43="",N($C43)=0),"",$E43/$C43) -> 0.13833333 | H43: =IF($A43="","",MAX(0,$D43-$E43)) -> 237 | I43: =IF($A43="","",$E43+$H43) -> 320 | J43: =IF($A43="","",IF($E43>$C43,"Budget dépassé",IF($I43>$C43,"Dépassement projeté",IF(AND($A43<>"",$B43<>"Confirmé",$E43>0),"Pointé sur source non confirmée",""))))
A44: =IF(Financement!$A5="","",Financement!$A5) -> Client A | B44: =IF($A44="","",Financement!$B5) -> Confirmé | C44: =IF($A44="","",Financement!$D5) -> 900 | D44: =IF($A44="","",Financement!$E5) -> 1020 | E44: =IF($A44="","",SUMIF(Pointage!$E$4:$E$303,$A44,Pointage!$F$4:$F$303)) -> 60 | F44: =IF($A44="","",$C44-$E44) -> 840 | G44: =IF(OR($A44="",N($C44)=0),"",$E44/$C44) -> 0.066666667 | H44: =IF($A44="","",MAX(0,$D44-$E44)) -> 960 | I44: =IF($A44="","",$E44+$H44) -> 1020 | J44: =IF($A44="","",IF($E44>$C44,"Budget dépassé",IF($I44>$C44,"Dépassement projeté",IF(AND($A44<>"",$B44<>"Confirmé",$E44>0),"Pointé sur source non confirmée","")))) -> Dépassement projeté
A45: =IF(Financement!$A6="","",Financement!$A6) -> Subvention | B45: =IF($A45="","",Financement!$B6) -> Pressenti | C45: =IF($A45="","",Financement!$D6) -> 300 | D45: =IF($A45="","",Financement!$E6) -> 180 | E45: =IF($A45="","",SUMIF(Pointage!$E$4:$E$303,$A45,Pointage!$F$4:$F$303)) -> 0 | F45: =IF($A45="","",$C45-$E45) -> 300 | G45: =IF(OR($A45="",N($C45)=0),"",$E45/$C45) -> 0 | H45: =IF($A45="","",MAX(0,$D45-$E45)) -> 180 | I45: =IF($A45="","",$E45+$H45) -> 180 | J45: =IF($A45="","",IF($E45>$C45,"Budget dépassé",IF($I45>$C45,"Dépassement projeté",IF(AND($A45<>"",$B45<>"Confirmé",$E45>0),"Pointé sur source non confirmée",""))))
A46: =IF(Financement!$A7="","",Financement!$A7) -> Client B | B46: =IF($A46="","",Financement!$B7) -> Option | C46: =IF($A46="","",Financement!$D7) -> 400 | D46: =IF($A46="","",Financement!$E7) -> 100 | E46: =IF($A46="","",SUMIF(Pointage!$E$4:$E$303,$A46,Pointage!$F$4:$F$303)) -> 0 | F46: =IF($A46="","",$C46-$E46) -> 400 | G46: =IF(OR($A46="",N($C46)=0),"",$E46/$C46) -> 0 | H46: =IF($A46="","",MAX(0,$D46-$E46)) -> 100 | I46: =IF($A46="","",$E46+$H46) -> 100 | J46: =IF($A46="","",IF($E46>$C46,"Budget dépassé",IF($I46>$C46,"Dépassement projeté",IF(AND($A46<>"",$B46<>"Confirmé",$E46>0),"Pointé sur source non confirmée",""))))
A47: =IF(Financement!$A8="","",Financement!$A8) | B47: =IF($A47="","",Financement!$B8) | C47: =IF($A47="","",Financement!$D8) | D47: =IF($A47="","",Financement!$E8) | E47: =IF($A47="","",SUMIF(Pointage!$E$4:$E$303,$A47,Pointage!$F$4:$F$303)) | F47: =IF($A47="","",$C47-$E47) | G47: =IF(OR($A47="",N($C47)=0),"",$E47/$C47) | H47: =IF($A47="","",MAX(0,$D47-$E47)) | I47: =IF($A47="","",$E47+$H47) | J47: =IF($A47="","",IF($E47>$C47,"Budget dépassé",IF($I47>$C47,"Dépassement projeté",IF(AND($A47<>"",$B47<>"Confirmé",$E47>0),"Pointé sur source non confirmée",""))))
A48: =IF(Financement!$A9="","",Financement!$A9) | B48: =IF($A48="","",Financement!$B9) | C48: =IF($A48="","",Financement!$D9) | D48: =IF($A48="","",Financement!$E9) | E48: =IF($A48="","",SUMIF(Pointage!$E$4:$E$303,$A48,Pointage!$F$4:$F$303)) | F48: =IF($A48="","",$C48-$E48) | G48: =IF(OR($A48="",N($C48)=0),"",$E48/$C48) | H48: =IF($A48="","",MAX(0,$D48-$E48)) | I48: =IF($A48="","",$E48+$H48) | J48: =IF($A48="","",IF($E48>$C48,"Budget dépassé",IF($I48>$C48,"Dépassement projeté",IF(AND($A48<>"",$B48<>"Confirmé",$E48>0),"Pointé sur source non confirmée",""))))
A49: =IF(Financement!$A10="","",Financement!$A10) | B49: =IF($A49="","",Financement!$B10) | C49: =IF($A49="","",Financement!$D10) | D49: =IF($A49="","",Financement!$E10) | E49: =IF($A49="","",SUMIF(Pointage!$E$4:$E$303,$A49,Pointage!$F$4:$F$303)) | F49: =IF($A49="","",$C49-$E49) | G49: =IF(OR($A49="",N($C49)=0),"",$E49/$C49) | H49: =IF($A49="","",MAX(0,$D49-$E49)) | I49: =IF($A49="","",$E49+$H49) | J49: =IF($A49="","",IF($E49>$C49,"Budget dépassé",IF($I49>$C49,"Dépassement projeté",IF(AND($A49<>"",$B49<>"Confirmé",$E49>0),"Pointé sur source non confirmée",""))))
A50: =IF(Financement!$A11="","",Financement!$A11) | B50: =IF($A50="","",Financement!$B11) | C50: =IF($A50="","",Financement!$D11) | D50: =IF($A50="","",Financement!$E11) | E50: =IF($A50="","",SUMIF(Pointage!$E$4:$E$303,$A50,Pointage!$F$4:$F$303)) | F50: =IF($A50="","",$C50-$E50) | G50: =IF(OR($A50="",N($C50)=0),"",$E50/$C50) | H50: =IF($A50="","",MAX(0,$D50-$E50)) | I50: =IF($A50="","",$E50+$H50) | J50: =IF($A50="","",IF($E50>$C50,"Budget dépassé",IF($I50>$C50,"Dépassement projeté",IF(AND($A50<>"",$B50<>"Confirmé",$E50>0),"Pointé sur source non confirmée",""))))
A51: =IF(Financement!$A12="","",Financement!$A12) | B51: =IF($A51="","",Financement!$B12) | C51: =IF($A51="","",Financement!$D12) | D51: =IF($A51="","",Financement!$E12) | E51: =IF($A51="","",SUMIF(Pointage!$E$4:$E$303,$A51,Pointage!$F$4:$F$303)) | F51: =IF($A51="","",$C51-$E51) | G51: =IF(OR($A51="",N($C51)=0),"",$E51/$C51) | H51: =IF($A51="","",MAX(0,$D51-$E51)) | I51: =IF($A51="","",$E51+$H51) | J51: =IF($A51="","",IF($E51>$C51,"Budget dépassé",IF($I51>$C51,"Dépassement projeté",IF(AND($A51<>"",$B51<>"Confirmé",$E51>0),"Pointé sur source non confirmée",""))))
A52: =IF(Financement!$A13="","",Financement!$A13) | B52: =IF($A52="","",Financement!$B13) | C52: =IF($A52="","",Financement!$D13) | D52: =IF($A52="","",Financement!$E13) | E52: =IF($A52="","",SUMIF(Pointage!$E$4:$E$303,$A52,Pointage!$F$4:$F$303)) | F52: =IF($A52="","",$C52-$E52) | G52: =IF(OR($A52="",N($C52)=0),"",$E52/$C52) | H52: =IF($A52="","",MAX(0,$D52-$E52)) | I52: =IF($A52="","",$E52+$H52) | J52: =IF($A52="","",IF($E52>$C52,"Budget dépassé",IF($I52>$C52,"Dépassement projeté",IF(AND($A52<>"",$B52<>"Confirmé",$E52>0),"Pointé sur source non confirmée",""))))
A53: =IF(Financement!$A14="","",Financement!$A14) | B53: =IF($A53="","",Financement!$B14) | C53: =IF($A53="","",Financement!$D14) | D53: =IF($A53="","",Financement!$E14) | E53: =IF($A53="","",SUMIF(Pointage!$E$4:$E$303,$A53,Pointage!$F$4:$F$303)) | F53: =IF($A53="","",$C53-$E53) | G53: =IF(OR($A53="",N($C53)=0),"",$E53/$C53) | H53: =IF($A53="","",MAX(0,$D53-$E53)) | I53: =IF($A53="","",$E53+$H53) | J53: =IF($A53="","",IF($E53>$C53,"Budget dépassé",IF($I53>$C53,"Dépassement projeté",IF(AND($A53<>"",$B53<>"Confirmé",$E53>0),"Pointé sur source non confirmée",""))))
A54: =IF(Financement!$A15="","",Financement!$A15) | B54: =IF($A54="","",Financement!$B15) | C54: =IF($A54="","",Financement!$D15) | D54: =IF($A54="","",Financement!$E15) | E54: =IF($A54="","",SUMIF(Pointage!$E$4:$E$303,$A54,Pointage!$F$4:$F$303)) | F54: =IF($A54="","",$C54-$E54) | G54: =IF(OR($A54="",N($C54)=0),"",$E54/$C54) | H54: =IF($A54="","",MAX(0,$D54-$E54)) | I54: =IF($A54="","",$E54+$H54) | J54: =IF($A54="","",IF($E54>$C54,"Budget dépassé",IF($I54>$C54,"Dépassement projeté",IF(AND($A54<>"",$B54<>"Confirmé",$E54>0),"Pointé sur source non confirmée",""))))
... A57: =IF(Financement!$A18="","",Financement!$A18) | B57: =IF($A57="","",Financement!$B18) | C57: =IF($A57="","",Financement!$D18) | D57: =IF($A57="","",Financement!$E18) | E57: =IF($A57="","",SUMIF(Pointage!$E$4:$E$303,$A57,Pointage!$F$4:$F$303)) | F57: =IF($A57="","",$C57-$E57) | G57: =IF(OR($A57="",N($C57)=0),"",$E57/$C57) | H57: =IF($A57="","",MAX(0,$D57-$E57)) | I57: =IF($A57="","",$E57+$H57) | J57: =IF($A57="","",IF($E57>$C57,"Budget dépassé",IF($I57>$C57,"Dépassement projeté",IF(AND($A57<>"",$B57<>"Confirmé",$E57>0),"Pointé sur source non confirmée",""))))
A58: TOTAL | C58: =SUM(C43:C57) -> 2200 | D58: =SUM(D43:D57) -> 1620 | E58: =SUM(E43:E57) -> 143 | F58: =SUM(F43:F57) -> 2057 | G58: =IFERROR(E58/C58,0) -> 0.065 | H58: =SUM(H43:H57) -> 1477 | I58: =SUM(I43:I57) -> 1620
A61: RÉFÉRENTIEL | C61: SUIVI VIVANT
A62: Mois | B62: Prévu cumulé | C62: Pointé du mois | D62: Pointé cumulé | E62: Écart cumulé | F62: Avancement cumulé
A63: 46266 | B63: =SUM(Gantt!$J$34:J$34) -> 80 | C63: =SUMIF(Pointage!$G$4:$G$303,$A63,Pointage!$F$4:$F$303) -> 83 | D63: =SUM($C$63:$C63) -> 83 | E63: =$D63-$B63 -> 3 | F63: =IFERROR($D63/Gantt!$G$34,0) -> 0.051234568
A64: 46296 | B64: =SUM(Gantt!$J$34:K$34) -> 400 | C64: =SUMIF(Pointage!$G$4:$G$303,$A64,Pointage!$F$4:$F$303) -> 60 | D64: =SUM($C$63:$C64) -> 143 | E64: =$D64-$B64 -> -257 | F64: =IFERROR($D64/Gantt!$G$34,0) -> 0.088271605
A65: 46327 | B65: =SUM(Gantt!$J$34:L$34) -> 720 | C65: =SUMIF(Pointage!$G$4:$G$303,$A65,Pointage!$F$4:$F$303) -> 0 | D65: =SUM($C$63:$C65) -> 143 | E65: =$D65-$B65 -> -577 | F65: =IFERROR($D65/Gantt!$G$34,0) -> 0.088271605
A66: 46357 | B66: =SUM(Gantt!$J$34:M$34) -> 1040 | C66: =SUMIF(Pointage!$G$4:$G$303,$A66,Pointage!$F$4:$F$303) -> 0 | D66: =SUM($C$63:$C66) -> 143 | E66: =$D66-$B66 -> -897 | F66: =IFERROR($D66/Gantt!$G$34,0) -> 0.088271605
A67: 46388 | B67: =SUM(Gantt!$J$34:N$34) -> 1360 | C67: =SUMIF(Pointage!$G$4:$G$303,$A67,Pointage!$F$4:$F$303) -> 0 | D67: =SUM($C$63:$C67) -> 143 | E67: =$D67-$B67 -> -1217 | F67: =IFERROR($D67/Gantt!$G$34,0) -> 0.088271605
A68: 46419 | B68: =SUM(Gantt!$J$34:O$34) -> 1620 | C68: =SUMIF(Pointage!$G$4:$G$303,$A68,Pointage!$F$4:$F$303) -> 0 | D68: =SUM($C$63:$C68) -> 143 | E68: =$D68-$B68 -> -1477 | F68: =IFERROR($D68/Gantt!$G$34,0) -> 0.088271605
A69: 46447 | B69: =SUM(Gantt!$J$34:P$34) -> 1620 | C69: =SUMIF(Pointage!$G$4:$G$303,$A69,Pointage!$F$4:$F$303) -> 0 | D69: =SUM($C$63:$C69) -> 143 | E69: =$D69-$B69 -> -1477 | F69: =IFERROR($D69/Gantt!$G$34,0) -> 0.088271605
A70: 46478 | B70: =SUM(Gantt!$J$34:Q$34) -> 1620 | C70: =SUMIF(Pointage!$G$4:$G$303,$A70,Pointage!$F$4:$F$303) -> 0 | D70: =SUM($C$63:$C70) -> 143 | E70: =$D70-$B70 -> -1477 | F70: =IFERROR($D70/Gantt!$G$34,0) -> 0.088271605
A71: 46508 | B71: =SUM(Gantt!$J$34:R$34) -> 1620 | C71: =SUMIF(Pointage!$G$4:$G$303,$A71,Pointage!$F$4:$F$303) -> 0 | D71: =SUM($C$63:$C71) -> 143 | E71: =$D71-$B71 -> -1477 | F71: =IFERROR($D71/Gantt!$G$34,0) -> 0.088271605
A72: 46539 | B72: =SUM(Gantt!$J$34:S$34) -> 1620 | C72: =SUMIF(Pointage!$G$4:$G$303,$A72,Pointage!$F$4:$F$303) -> 0 | D72: =SUM($C$63:$C72) -> 143 | E72: =$D72-$B72 -> -1477 | F72: =IFERROR($D72/Gantt!$G$34,0) -> 0.088271605
A73: 46569 | B73: =SUM(Gantt!$J$34:T$34) -> 1620 | C73: =SUMIF(Pointage!$G$4:$G$303,$A73,Pointage!$F$4:$F$303) -> 0 | D73: =SUM($C$63:$C73) -> 143 | E73: =$D73-$B73 -> -1477 | F73: =IFERROR($D73/Gantt!$G$34,0) -> 0.088271605
A74: 46600 | B74: =SUM(Gantt!$J$34:U$34) -> 1620 | C74: =SUMIF(Pointage!$G$4:$G$303,$A74,Pointage!$F$4:$F$303) -> 0 | D74: =SUM($C$63:$C74) -> 143 | E74: =$D74-$B74 -> -1477 | F74: =IFERROR($D74/Gantt!$G$34,0) -> 0.088271605
A75: 46631 | B75: =SUM(Gantt!$J$34:V$34) -> 1620 | C75: =SUMIF(Pointage!$G$4:$G$303,$A75,Pointage!$F$4:$F$303) -> 0 | D75: =SUM($C$63:$C75) -> 143 | E75: =$D75-$B75 -> -1477 | F75: =IFERROR($D75/Gantt!$G$34,0) -> 0.088271605
A76: 46661 | B76: =SUM(Gantt!$J$34:W$34) -> 1620 | C76: =SUMIF(Pointage!$G$4:$G$303,$A76,Pointage!$F$4:$F$303) -> 0 | D76: =SUM($C$63:$C76) -> 143 | E76: =$D76-$B76 -> -1477 | F76: =IFERROR($D76/Gantt!$G$34,0) -> 0.088271605
A77: 46692 | B77: =SUM(Gantt!$J$34:X$34) -> 1620 | C77: =SUMIF(Pointage!$G$4:$G$303,$A77,Pointage!$F$4:$F$303) -> 0 | D77: =SUM($C$63:$C77) -> 143 | E77: =$D77-$B77 -> -1477 | F77: =IFERROR($D77/Gantt!$G$34,0) -> 0.088271605
A78: 46722 | B78: =SUM(Gantt!$J$34:Y$34) -> 1620 | C78: =SUMIF(Pointage!$G$4:$G$303,$A78,Pointage!$F$4:$F$303) -> 0 | D78: =SUM($C$63:$C78) -> 143 | E78: =$D78-$B78 -> -1477 | F78: =IFERROR($D78/Gantt!$G$34,0) -> 0.088271605
A79: 46753 | B79: =SUM(Gantt!$J$34:Z$34) -> 1620 | C79: =SUMIF(Pointage!$G$4:$G$303,$A79,Pointage!$F$4:$F$303) -> 0 | D79: =SUM($C$63:$C79) -> 143 | E79: =$D79-$B79 -> -1477 | F79: =IFERROR($D79/Gantt!$G$34,0) -> 0.088271605
A80: 46784 | B80: =SUM(Gantt!$J$34:AA$34) -> 1620 | C80: =SUMIF(Pointage!$G$4:$G$303,$A80,Pointage!$F$4:$F$303) -> 0 | D80: =SUM($C$63:$C80) -> 143 | E80: =$D80-$B80 -> -1477 | F80: =IFERROR($D80/Gantt!$G$34,0) -> 0.088271605
A82: Écart cumulé positif = on a pointé moins que prévu à cette date (retard de consommation) ; négatif = on consomme plus vite que le plan.
